<INDIVIDUAL>
  <ID>subject2475</ID>
  <WRITING>
    <TITLE>Why does the Media hate esports so much?</TITLE>
    <DATE>2017-02-08 03:55:19</DATE>
    <TEXT></TEXT>
    <INFO>Reddit post</INFO>
  </WRITING>
  <WRITING>
    <TITLE>Why does the media hate esports?</TITLE>
    <DATE>2017-02-08 14:24:34</DATE>
    <TEXT></TEXT>
    <INFO>Reddit post</INFO>
  </WRITING>
  <WRITING>
    <TITLE>3 "tips" to play bastion like zylbrad</TITLE>
    <DATE>2017-02-10 20:03:41</DATE>
    <TEXT></TEXT>
    <INFO>Reddit post</INFO>
  </WRITING>
  <WRITING>
    <TITLE></TITLE>
    <DATE>2017-02-10 20:06:48</DATE>
    <TEXT>this isnt a glitch, you are just out of the swords's AOE</TEXT>
    <INFO>Reddit post</INFO>
  </WRITING>
  <WRITING>
    <TITLE>How to play bastion like zylbrad</TITLE>
    <DATE>2017-02-10 20:18:09</DATE>
    <TEXT></TEXT>
    <INFO>Reddit post</INFO>
  </WRITING>
  <WRITING>
    <TITLE></TITLE>
    <DATE>2017-02-11 01:00:20</DATE>
    <TEXT>comp is the most xp heavy, but i cant play more then 4 games in a row of it without getting bored</TEXT>
    <INFO>Reddit post</INFO>
  </WRITING>
  <WRITING>
    <TITLE></TITLE>
    <DATE>2017-02-11 01:07:02</DATE>
    <TEXT>I play pretty much only on xbox 1 and I have been in matches where guys on my team have used pc controls. Their accuracy is unusually high and in my opinion it creates an unfair comp experience(as it's easier to aim with mouse and keyboard)</TEXT>
    <INFO>Reddit post</INFO>
  </WRITING>
  <WRITING>
    <TITLE></TITLE>
    <DATE>2017-02-11 18:07:10</DATE>
    <TEXT>both, by the time the patch goes live, the patch certification process should be done for the consoles</TEXT>
    <INFO>Reddit post</INFO>
  </WRITING>
  <WRITING>
    <TITLE></TITLE>
    <DATE>2017-02-12 17:49:25</DATE>
    <TEXT>what rule did I break? I thought I followed the requirements. Im interested to know</TEXT>
    <INFO>Reddit post</INFO>
  </WRITING>
  <WRITING>
    <TITLE>Soldier 76 inspiration?</TITLE>
    <DATE>2017-02-12 18:46:44</DATE>
    <TEXT></TEXT>
    <INFO>Reddit post</INFO>
  </WRITING>
  <WRITING>
    <TITLE></TITLE>
    <DATE>2017-02-12 19:52:15</DATE>
    <TEXT>i'm aware, this was a theory about the in-game cosmetics and the name itself. This should support the theory why 76 himself took the name, not blizzard, I refrence this several times in the video.</TEXT>
    <INFO>Reddit post</INFO>
  </WRITING>
  <WRITING>
    <TITLE>Love Poems For Overwatch Players (try these to get a valentines date)</TITLE>
    <DATE>2017-02-13 03:12:57</DATE>
    <TEXT></TEXT>
    <INFO>Reddit post</INFO>
  </WRITING>
  <WRITING>
    <TITLE>Love Poems for Overwatch Players</TITLE>
    <DATE>2017-02-13 03:35:48</DATE>
    <TEXT></TEXT>
    <INFO>Reddit post</INFO>
  </WRITING>
  <WRITING>
    <TITLE>obviously I should have been a poet :)</TITLE>
    <DATE>2017-02-13 15:58:03</DATE>
    <TEXT></TEXT>
    <INFO>Reddit post</INFO>
  </WRITING>
  <WRITING>
    <TITLE></TITLE>
    <DATE>2017-02-13 16:00:51</DATE>
    <TEXT>watch out! justice is raining from abAAGHHHH</TEXT>
    <INFO>Reddit post</INFO>
  </WRITING>
  <WRITING>
    <TITLE></TITLE>
    <DATE>2017-02-13 16:02:57</DATE>
    <TEXT>MADA MADA</TEXT>
    <INFO>Reddit post</INFO>
  </WRITING>
  <WRITING>
    <TITLE></TITLE>
    <DATE>2017-02-21 22:37:41</DATE>
    <TEXT>Does anyone realize that this article is written in 2017 in the Overwatch world? If i'm right, this kid would be about 50 during the events of the game.</TEXT>
    <INFO>Reddit post</INFO>
  </WRITING>
  <WRITING>
    <TITLE>The Ultimate Overwatch MIXTAPE (original music owned by Blizzard Entertainment)</TITLE>
    <DATE>2017-03-10 21:46:32</DATE>
    <TEXT></TEXT>
    <INFO>Reddit post</INFO>
  </WRITING>
  <WRITING>
    <TITLE>My Overwatch Mixtape</TITLE>
    <DATE>2017-03-10 22:16:47</DATE>
    <TEXT></TEXT>
    <INFO>Reddit post</INFO>
  </WRITING>
  <WRITING>
    <TITLE></TITLE>
    <DATE>2017-03-11 03:55:49</DATE>
    <TEXT>My best answer is that you are improving at the game, and the MMR system picks up on that. I will say, Ive certainly never got placed at a career high......</TEXT>
    <INFO>Reddit post</INFO>
  </WRITING>
  <WRITING>
    <TITLE></TITLE>
    <DATE>2017-03-11 04:02:23</DATE>
    <TEXT>Ok, So the SR system is based of your MMR (an invisible ranking only Blizzard can see) The wins or losses of placement games don't really effect your placement rank. This is especially true if you are like me and play upwards of 200 games per season. The game already has a lot of information on you, and the idea of the placement games is just to verify that your MMR is as accurate as possible. For instance, my season high for S3 was 3685. After going 5-5 on placement games, I ended up at 3541, just into masters. This was a pretty lengthy explanation, but I hope it helped. :)</TEXT>
    <INFO>Reddit post</INFO>
  </WRITING>
  <WRITING>
    <TITLE></TITLE>
    <DATE>2017-03-11 04:35:11</DATE>
    <TEXT>on xbox you can look for teams on the Overwatch Competetive group</TEXT>
    <INFO>Reddit post</INFO>
  </WRITING>
  <WRITING>
    <TITLE></TITLE>
    <DATE>2017-03-11 15:38:52</DATE>
    <TEXT>Ok, so to answer your initial question, yes. Your QP MMR and comp MMR are separate. Also, the only season to completely reset MMR was between S1 and S2. (because of the change in the ranking system.)</TEXT>
    <INFO>Reddit post</INFO>
  </WRITING>
  <WRITING>
    <TITLE>My Sombra Spanish Class Adventure</TITLE>
    <DATE>2017-03-11 15:44:16</DATE>
    <TEXT>So in my spanish class this week, my teacher asked me to turn out the lights. When doing so I yelled APAGANDO LAS LUCES. My teacher asked me how I knew what that meant(cuz i'm garbage at spanish) and I told her it was from a video game. She was actually pretty interested in the topic, and let me play as Sombra on Overwatch for my weekly "Spanish Study Time" homework. 2 words: AHA YEAH</TEXT>
    <INFO>Reddit post</INFO>
  </WRITING>
  <WRITING>
    <TITLE>Why the Medal System is a bit broken</TITLE>
    <DATE>2017-03-11 19:53:29</DATE>
    <TEXT></TEXT>
    <INFO>Reddit post</INFO>
  </WRITING>
  <WRITING>
    <TITLE></TITLE>
    <DATE>2017-03-11 20:14:18</DATE>
    <TEXT>the problem with this is that people could manipulate the system in groups. If a loss was going to occur, the group members could take turns leaving, and the rest of the group would take no penalty. Also, there already is a reduced SR drop for a loss when a team is down a player.</TEXT>
    <INFO>Reddit post</INFO>
  </WRITING>
  <WRITING>
    <TITLE></TITLE>
    <DATE>2017-03-11 20:18:15</DATE>
    <TEXT>Sup guys, Ive spent 6 hours mixing this mini song compiled from the Overwatch Game soundtrack. Comments? https://www.youtube.com/watch?v=giGmNTPGIOQ amp;t=11s</TEXT>
    <INFO>Reddit post</INFO>
  </WRITING>
  <WRITING>
    <TITLE>Best Ways To Earn More XP (without XP farming)</TITLE>
    <DATE>2017-03-13 02:04:14</DATE>
    <TEXT></TEXT>
    <INFO>Reddit post</INFO>
  </WRITING>
  <WRITING>
    <TITLE>Overwatch Weapon Sounds Quiz EXTRA HARD EDITION</TITLE>
    <DATE>2017-03-25 18:10:12</DATE>
    <TEXT></TEXT>
    <INFO>Reddit post</INFO>
  </WRITING>
  <WRITING>
    <TITLE></TITLE>
    <DATE>2017-03-26 04:50:31</DATE>
    <TEXT>lol, next up: ULTRA CRAZY INSANE DIFFICULT CLICKBAIT EDITION</TEXT>
    <INFO>Reddit post</INFO>
  </WRITING>
  <WRITING>
    <TITLE>What Happens when you Pick Widowmaker in Competetive (joke)</TITLE>
    <DATE>2017-03-26 04:55:40</DATE>
    <TEXT></TEXT>
    <INFO>Reddit post</INFO>
  </WRITING>
  <WRITING>
    <TITLE>What Happens when you Pick Widowmaker in Competetive (joke)</TITLE>
    <DATE>2017-03-26 05:05:41</DATE>
    <TEXT></TEXT>
    <INFO>Reddit post</INFO>
  </WRITING>
  <WRITING>
    <TITLE>When you ask someone out and they shoot you down</TITLE>
    <DATE>2017-03-27 01:07:11</DATE>
    <TEXT></TEXT>
    <INFO>Reddit post</INFO>
  </WRITING>
  <WRITING>
    <TITLE>Dear Bungie, Please don't Screw up Destiny 2</TITLE>
    <DATE>2017-03-31 01:25:32</DATE>
    <TEXT></TEXT>
    <INFO>Reddit post</INFO>
  </WRITING>
  <WRITING>
    <TITLE></TITLE>
    <DATE>2017-04-09 16:06:04</DATE>
    <TEXT>that is simply beautiful</TEXT>
    <INFO>Reddit post</INFO>
  </WRITING>
  <WRITING>
    <TITLE></TITLE>
    <DATE>2017-04-09 16:07:40</DATE>
    <TEXT>AHAHAHAH GOT YOU</TEXT>
    <INFO>Reddit post</INFO>
  </WRITING>
  <WRITING>
    <TITLE></TITLE>
    <DATE>2017-04-09 16:08:40</DATE>
    <TEXT>TACTICAL NUKE INBOUND</TEXT>
    <INFO>Reddit post</INFO>
  </WRITING>
  <WRITING>
    <TITLE>Young Genji and Young Hanzo Fight Over a Teddy Bear(Skit)</TITLE>
    <DATE>2017-04-09 16:09:54</DATE>
    <TEXT></TEXT>
    <INFO>Reddit post</INFO>
  </WRITING>
  <WRITING>
    <TITLE>At level 525, this is my career profile</TITLE>
    <DATE>2017-06-21 22:10:38</DATE>
    <TEXT></TEXT>
    <INFO>Reddit post</INFO>
  </WRITING>
  <WRITING>
    <TITLE>How Embarrassing....</TITLE>
    <DATE>2017-07-02 18:45:50</DATE>
    <TEXT></TEXT>
    <INFO>Reddit post</INFO>
  </WRITING>
  <WRITING>
    <TITLE>Overwatch Mixtape (youtube link)</TITLE>
    <DATE>2017-07-06 18:26:57</DATE>
    <TEXT></TEXT>
    <INFO>Reddit post</INFO>
  </WRITING>
  <WRITING>
    <TITLE>What Doomfist Could Have Been...</TITLE>
    <DATE>2017-07-18 03:39:20</DATE>
    <TEXT></TEXT>
    <INFO>Reddit post</INFO>
  </WRITING>
  <WRITING>
    <TITLE></TITLE>
    <DATE>2017-08-20 21:36:52</DATE>
    <TEXT>Feature Scarce's glorious return to YouTube</TEXT>
    <INFO>Reddit post</INFO>
  </WRITING>
  <WRITING>
    <TITLE>This "memory hook" on the vocab website my school uses</TITLE>
    <DATE>2017-08-22 00:11:34</DATE>
    <TEXT></TEXT>
    <INFO>Reddit post</INFO>
  </WRITING>
  <WRITING>
    <TITLE>I want to die</TITLE>
    <DATE>2017-08-23 02:54:29</DATE>
    <TEXT></TEXT>
    <INFO>Reddit post</INFO>
  </WRITING>
  <WRITING>
    <TITLE></TITLE>
    <DATE>2017-09-05 02:20:00</DATE>
    <TEXT>Hey y'all, I was wondering what the best way is to EZ over clock my MSI 1060 card. I was able to get 4.8 ghtz out of my CPU using EZ over clock, and am not real comfortable messing with voltage. I can't find an opinion for GPU overclock tweaking anywhere in my UEFI or my windows system page. I can post other specs if necessary. Thanks for any help you can give.</TEXT>
    <INFO>Reddit post</INFO>
  </WRITING>
  <WRITING>
    <TITLE></TITLE>
    <DATE>2017-09-13 14:22:00</DATE>
    <TEXT>Try OBS, It's free and captures the audio output at whatever level you set it.</TEXT>
    <INFO>Reddit post</INFO>
  </WRITING>
  <WRITING>
    <TITLE></TITLE>
    <DATE>2017-09-13 14:32:14</DATE>
    <TEXT>I have the Corsair Spec Alpha, great looking and tool-less side panel removal.</TEXT>
    <INFO>Reddit post</INFO>
  </WRITING>
  <WRITING>
    <TITLE></TITLE>
    <DATE>2017-09-13 18:47:52</DATE>
    <TEXT>In that case, if you are running an Nvidia card you can record game clips with the "GeForce Experience" app. You can bind the recording to a certain key and set it to record the 30 seconds before hitting that key.</TEXT>
    <INFO>Reddit post</INFO>
  </WRITING>
  <WRITING>
    <TITLE></TITLE>
    <DATE>2017-09-14 00:42:19</DATE>
    <TEXT>Crisis (Chill guys it's just a joke)</TEXT>
    <INFO>Reddit post</INFO>
  </WRITING>
  <WRITING>
    <TITLE></TITLE>
    <DATE>2017-09-16 03:56:17</DATE>
    <TEXT>Go look on kinguin.com. You can buy a windows 10 code for $25 on there. I can personally vouch for it as I purchased a windows 10 pro key with no issues.</TEXT>
    <INFO>Reddit post</INFO>
  </WRITING>
  <WRITING>
    <TITLE>Found in my math book; someone could use a RAM upgrade....</TITLE>
    <DATE>2017-09-16 03:58:45</DATE>
    <TEXT></TEXT>
    <INFO>Reddit post</INFO>
  </WRITING>
  <WRITING>
    <TITLE>My Dad's "really good" PC from high school, press F to pay respects</TITLE>
    <DATE>2017-09-17 18:46:40</DATE>
    <TEXT></TEXT>
    <INFO>Reddit post</INFO>
  </WRITING>
  <WRITING>
    <TITLE></TITLE>
    <DATE>2017-09-17 20:24:35</DATE>
    <TEXT>I'd have a look at a higher end Core I3, you really don't need a ton of CPU power to game. You probably would be better off saving on the processor and going for a 3GB GTX1060</TEXT>
    <INFO>Reddit post</INFO>
  </WRITING>
  <WRITING>
    <TITLE></TITLE>
    <DATE>2017-09-17 20:30:25</DATE>
    <TEXT>Why did the scarecrow win the award....? He was outstanding in his field.</TEXT>
    <INFO>Reddit post</INFO>
  </WRITING>
  <WRITING>
    <TITLE></TITLE>
    <DATE>2017-09-17 21:36:53</DATE>
    <TEXT>I might actually give that a try, maybe give it back to my dad for Christmas or something?</TEXT>
    <INFO>Reddit post</INFO>
  </WRITING>
  <WRITING>
    <TITLE></TITLE>
    <DATE>2017-09-17 23:08:21</DATE>
    <TEXT>37* ( but still true)</TEXT>
    <INFO>Reddit post</INFO>
  </WRITING>
  <WRITING>
    <TITLE></TITLE>
    <DATE>2017-09-18 05:07:13</DATE>
    <TEXT>Actually it is, no mods made</TEXT>
    <INFO>Reddit post</INFO>
  </WRITING>
  <WRITING>
    <TITLE></TITLE>
    <DATE>2017-09-20 13:23:49</DATE>
    <TEXT>Try tunnelbear now, FREE FOR 30 DAYZ!!! pcmrftw</TEXT>
    <INFO>Reddit post</INFO>
  </WRITING>
  <WRITING>
    <TITLE>Found this at Walmart; we #8217;re taking over!</TITLE>
    <DATE>2017-09-23 18:21:52</DATE>
    <TEXT></TEXT>
    <INFO>Reddit post</INFO>
  </WRITING>
  <WRITING>
    <TITLE>Decided to stream PUBG for the first time, was not disappointed...</TITLE>
    <DATE>2017-10-01 23:39:46</DATE>
    <TEXT></TEXT>
    <INFO>Reddit post</INFO>
  </WRITING>
  <WRITING>
    <TITLE>Streamed PUBG, Community did not disappoint...</TITLE>
    <DATE>2017-10-02 02:24:36</DATE>
    <TEXT></TEXT>
    <INFO>Reddit post</INFO>
  </WRITING>
  <WRITING>
    <TITLE>Heard you guys like money shots...</TITLE>
    <DATE>2017-10-04 04:34:31</DATE>
    <TEXT></TEXT>
    <INFO>Reddit post</INFO>
  </WRITING>
  <WRITING>
    <TITLE>My  #8220;MSI Certified #8221; mac has ascended!</TITLE>
    <DATE>2017-10-07 22:54:44</DATE>
    <TEXT></TEXT>
    <INFO>Reddit post</INFO>
  </WRITING>
  <WRITING>
    <TITLE></TITLE>
    <DATE>2017-10-08 00:21:52</DATE>
    <TEXT>Bro, he #8217;s my homie...</TEXT>
    <INFO>Reddit post</INFO>
  </WRITING>
  <WRITING>
    <TITLE></TITLE>
    <DATE>2017-10-08 19:42:57</DATE>
    <TEXT>This belongs on r/overwatch</TEXT>
    <INFO>Reddit post</INFO>
  </WRITING>
  <WRITING>
    <TITLE>Flam-BOI-unt</TITLE>
    <DATE>2017-10-10 03:31:58</DATE>
    <TEXT></TEXT>
    <INFO>Reddit post</INFO>
  </WRITING>
  <WRITING>
    <TITLE>Shia is unrelenting...</TITLE>
    <DATE>2017-10-10 03:33:01</DATE>
    <TEXT></TEXT>
    <INFO>Reddit post</INFO>
  </WRITING>
  <WRITING>
    <TITLE>I guess China really is number 1....</TITLE>
    <DATE>2017-10-12 16:35:40</DATE>
    <TEXT></TEXT>
    <INFO>Reddit post</INFO>
  </WRITING>
  <WRITING>
    <TITLE>Membene.exe has stopped functioning...</TITLE>
    <DATE>2017-10-13 15:16:55</DATE>
    <TEXT></TEXT>
    <INFO>Reddit post</INFO>
  </WRITING>
  <WRITING>
    <TITLE>Y tho</TITLE>
    <DATE>2017-10-17 18:03:15</DATE>
    <TEXT></TEXT>
    <INFO>Reddit post</INFO>
  </WRITING>
  <WRITING>
    <TITLE>My finished sleeper build (specs in comments)</TITLE>
    <DATE>2017-10-29 17:54:12</DATE>
    <TEXT></TEXT>
    <INFO>Reddit post</INFO>
  </WRITING>
  <WRITING>
    <TITLE></TITLE>
    <DATE>2017-10-29 17:56:28</DATE>
    <TEXT>Ryzen 5 1500x Rx 550 16 gb ddr4 3 tb hdd</TEXT>
    <INFO>Reddit post</INFO>
  </WRITING>
  <WRITING>
    <TITLE></TITLE>
    <DATE>2017-10-29 20:00:33</DATE>
    <TEXT>Yeah, eventually I #8217;d like to get a 1060 6 gb but I #8217;m worried it would run too hot. I plan to get an external water block to keep it all more frosty, just don #8217;t have the funds right now.</TEXT>
    <INFO>Reddit post</INFO>
  </WRITING>
  <WRITING>
    <TITLE></TITLE>
    <DATE>2017-10-29 20:02:16</DATE>
    <TEXT>Pretty hot, unsurprisingly. I cut out 2 fan vents on the bottom and 1 behind the front IO. That certainly helps but water cooled would be ideal.</TEXT>
    <INFO>Reddit post</INFO>
  </WRITING>
  <WRITING>
    <TITLE></TITLE>
    <DATE>2017-10-30 04:00:48</DATE>
    <TEXT>They do! I just needed to plug the prongs on the mobo. It was surprisingly easy.</TEXT>
    <INFO>Reddit post</INFO>
  </WRITING>
  <WRITING>
    <TITLE></TITLE>
    <DATE>2017-10-30 04:02:52</DATE>
    <TEXT>It is actually, building it for his Christmas present.</TEXT>
    <INFO>Reddit post</INFO>
  </WRITING>
  <WRITING>
    <TITLE></TITLE>
    <DATE>2017-11-07 16:14:44</DATE>
    <TEXT>Play of the game....</TEXT>
    <INFO>Reddit post</INFO>
  </WRITING>
  <WRITING>
    <TITLE></TITLE>
    <DATE>2017-11-07 16:17:58</DATE>
    <TEXT>Known, it is</TEXT>
    <INFO>Reddit post</INFO>
  </WRITING>
  <WRITING>
    <TITLE></TITLE>
    <DATE>2017-12-14 22:07:48</DATE>
    <TEXT>This is just an example of unelected government officials making decisions without real consequences. Decisions like this go beyond something any old appointed official should be able to dictate. If the FCC was an elected  #8220;office #8221; , representatives would be forced to vote with the majority for fear of not being re-elected.</TEXT>
    <INFO>Reddit post</INFO>
  </WRITING>
  <WRITING>
    <TITLE></TITLE>
    <DATE>2017-12-20 02:45:01</DATE>
    <TEXT>Have you ever had issues with pets, animals, etc?</TEXT>
    <INFO>Reddit post</INFO>
  </WRITING>
  <WRITING>
    <TITLE></TITLE>
    <DATE>2017-12-23 16:12:58</DATE>
    <TEXT>NORTH KOREA NUMBA JUAN</TEXT>
    <INFO>Reddit post</INFO>
  </WRITING>
  <WRITING>
    <TITLE></TITLE>
    <DATE>2017-12-23 18:07:39</DATE>
    <TEXT>I uh, use a banana holder that I painted black</TEXT>
    <INFO>Reddit post</INFO>
  </WRITING>
  <WRITING>
    <TITLE></TITLE>
    <DATE>2017-12-27 06:17:04</DATE>
    <TEXT>TUNNELBEAR IS THE SIMPLE, EASY TO USE VPN</TEXT>
    <INFO>Reddit post</INFO>
  </WRITING>
  <WRITING>
    <TITLE>My desires are... unconventional</TITLE>
    <DATE>2017-12-27 16:57:57</DATE>
    <TEXT></TEXT>
    <INFO>Reddit post</INFO>
  </WRITING>
  <WRITING>
    <TITLE></TITLE>
    <DATE>2017-12-28 01:05:59</DATE>
    <TEXT>Not a monitor issue, I #8217;ve seen it myself on both PC and Xbox</TEXT>
    <INFO>Reddit post</INFO>
  </WRITING>
  <WRITING>
    <TITLE></TITLE>
    <DATE>2018-01-04 17:09:55</DATE>
    <TEXT>Comic sans</TEXT>
    <INFO>Reddit post</INFO>
  </WRITING>
  <WRITING>
    <TITLE>Union station done goofed</TITLE>
    <DATE>2018-01-19 15:29:51</DATE>
    <TEXT></TEXT>
    <INFO>Reddit post</INFO>
  </WRITING>
  <WRITING>
    <TITLE>Flavor town</TITLE>
    <DATE>2018-01-28 01:14:49</DATE>
    <TEXT></TEXT>
    <INFO>Reddit post</INFO>
  </WRITING>
  <WRITING>
    <TITLE>How do fat people break down barriers?</TITLE>
    <DATE>2018-02-04 02:44:10</DATE>
    <TEXT>By walking through them</TEXT>
    <INFO>Reddit post</INFO>
  </WRITING>
  <WRITING>
    <TITLE></TITLE>
    <DATE>2018-02-07 05:40:13</DATE>
    <TEXT>Dead by daylight would be awesome! Thanks!</TEXT>
    <INFO>Reddit post</INFO>
  </WRITING>
  <WRITING>
    <TITLE></TITLE>
    <DATE>2018-02-13 02:25:37</DATE>
    <TEXT>r/fellowkids</TEXT>
    <INFO>Reddit post</INFO>
  </WRITING>
  <WRITING>
    <TITLE>This year #8217;s valentines</TITLE>
    <DATE>2018-02-13 04:10:56</DATE>
    <TEXT></TEXT>
    <INFO>Reddit post</INFO>
  </WRITING>
  <WRITING>
    <TITLE></TITLE>
    <DATE>2018-02-13 22:00:44</DATE>
    <TEXT>Rules of survival master race  #128170;</TEXT>
    <INFO>Reddit post</INFO>
  </WRITING>
  <WRITING>
    <TITLE></TITLE>
    <DATE>2018-02-14 18:09:01</DATE>
    <TEXT>!redditdirt</TEXT>
    <INFO>Reddit post</INFO>
  </WRITING>
  <WRITING>
    <TITLE>Wrong Number (x-post r/oldpeoplefacebook)</TITLE>
    <DATE>2018-02-14 18:51:37</DATE>
    <TEXT></TEXT>
    <INFO>Reddit post</INFO>
  </WRITING>
  <WRITING>
    <TITLE>Bill Nye= Lady Slayer</TITLE>
    <DATE>2018-02-15 04:34:59</DATE>
    <TEXT></TEXT>
    <INFO>Reddit post</INFO>
  </WRITING>
  <WRITING>
    <TITLE></TITLE>
    <DATE>2018-02-15 16:36:34</DATE>
    <TEXT>Yes, we are competing in Kansas City in a few weeks</TEXT>
    <INFO>Reddit post</INFO>
  </WRITING>
  <WRITING>
    <TITLE></TITLE>
    <DATE>2018-02-15 18:46:24</DATE>
    <TEXT>Lmao my English teacher would be disappointed</TEXT>
    <INFO>Reddit post</INFO>
  </WRITING>
  <WRITING>
    <TITLE></TITLE>
    <DATE>2018-02-16 06:18:18</DATE>
    <TEXT>Buy that merch</TEXT>
    <INFO>Reddit post</INFO>
  </WRITING>
  <WRITING>
    <TITLE></TITLE>
    <DATE>2018-02-16 06:20:15</DATE>
    <TEXT>I #8217;m not worried, we all bros here in Nebraska</TEXT>
    <INFO>Reddit post</INFO>
  </WRITING>
  <WRITING>
    <TITLE></TITLE>
    <DATE>2018-02-16 06:41:56</DATE>
    <TEXT>I can swim it in 18:56</TEXT>
    <INFO>Reddit post</INFO>
  </WRITING>
  <WRITING>
    <TITLE>The useless generation (X-post r/memes)</TITLE>
    <DATE>2018-02-19 01:54:30</DATE>
    <TEXT></TEXT>
    <INFO>Reddit post</INFO>
  </WRITING>
  <WRITING>
    <TITLE></TITLE>
    <DATE>2018-02-26 16:30:09</DATE>
    <TEXT>Plot twist</TEXT>
    <INFO>Reddit post</INFO>
  </WRITING>
  <WRITING>
    <TITLE>Tasty</TITLE>
    <DATE>2018-03-05 06:34:49</DATE>
    <TEXT></TEXT>
    <INFO>Reddit post</INFO>
  </WRITING>
  <WRITING>
    <TITLE></TITLE>
    <DATE>2018-03-07 05:39:16</DATE>
    <TEXT>r/photoshopbattles</TEXT>
    <INFO>Reddit post</INFO>
  </WRITING>
  <WRITING>
    <TITLE></TITLE>
    <DATE>2018-03-08 18:57:55</DATE>
    <TEXT>Ur gay lol</TEXT>
    <INFO>Reddit post</INFO>
  </WRITING>
  <WRITING>
    <TITLE></TITLE>
    <DATE>2018-03-09 03:43:11</DATE>
    <TEXT>Reviving this sub #128076;</TEXT>
    <INFO>Reddit post</INFO>
  </WRITING>
  <WRITING>
    <TITLE></TITLE>
    <DATE>2018-03-10 21:15:26</DATE>
    <TEXT>The fact this photo was taken sideways is almost more enraging then the sonic poster</TEXT>
    <INFO>Reddit post</INFO>
  </WRITING>
  <WRITING>
    <TITLE>Get got</TITLE>
    <DATE>2018-03-11 00:36:22</DATE>
    <TEXT></TEXT>
    <INFO>Reddit post</INFO>
  </WRITING>
  <WRITING>
    <TITLE></TITLE>
    <DATE>2018-03-12 01:49:37</DATE>
    <TEXT>Solid</TEXT>
    <INFO>Reddit post</INFO>
  </WRITING>
  <WRITING>
    <TITLE>Thoughts?</TITLE>
    <DATE>2018-03-12 02:03:50</DATE>
    <TEXT></TEXT>
    <INFO>Reddit post</INFO>
  </WRITING>
  <WRITING>
    <TITLE></TITLE>
    <DATE>2018-03-12 02:59:54</DATE>
    <TEXT>Punching trees</TEXT>
    <INFO>Reddit post</INFO>
  </WRITING>
  <WRITING>
    <TITLE>Sponsored teams: how did you go about forming relationships with your sponsors?</TITLE>
    <DATE>2018-03-14 15:09:32</DATE>
    <TEXT>Howdy guys, I #8217;m a coder/PR guy for a rookie team based out of Omaha NE. We got enough funding for our first year, It we will need more to expand our program any further. I #8217;ve noticed from watching videos of the regional competition that many of the teams are sponsored by engineering companies and the like. We got a grant from NASA to start out, it I was wondering who I should talk to for sponsorship opportunities. Any advice would be greatly appreciated.</TEXT>
    <INFO>Reddit post</INFO>
  </WRITING>
  <WRITING>
    <TITLE>A true story</TITLE>
    <DATE>2018-03-15 20:24:46</DATE>
    <TEXT></TEXT>
    <INFO>Reddit post</INFO>
  </WRITING>
  <WRITING>
    <TITLE>One two three four, I declare a meme war</TITLE>
    <DATE>2018-03-27 06:11:10</DATE>
    <TEXT></TEXT>
    <INFO>Reddit post</INFO>
  </WRITING>
  <WRITING>
    <TITLE>When war spreads to a random subreddit</TITLE>
    <DATE>2018-03-27 16:05:40</DATE>
    <TEXT></TEXT>
    <INFO>Reddit post</INFO>
  </WRITING>
  <WRITING>
    <TITLE>When you realize r/trebuchetmemes has 82 times as many subs as r/catapultmemes</TITLE>
    <DATE>2018-03-27 16:18:48</DATE>
    <TEXT></TEXT>
    <INFO>Reddit post</INFO>
  </WRITING>
  <WRITING>
    <TITLE></TITLE>
    <DATE>2018-03-27 16:26:53</DATE>
    <TEXT>No u</TEXT>
    <INFO>Reddit post</INFO>
  </WRITING>
  <WRITING>
    <TITLE></TITLE>
    <DATE>2018-03-27 23:29:13</DATE>
    <TEXT>Exposed</TEXT>
    <INFO>Reddit post</INFO>
  </WRITING>
  <WRITING>
    <TITLE>Newegg #8217;s 10/10 pricing</TITLE>
    <DATE>2018-03-28 18:13:49</DATE>
    <TEXT></TEXT>
    <INFO>Reddit post</INFO>
  </WRITING>
  <WRITING>
    <TITLE>When you #8217;re the first to post in a new subreddit</TITLE>
    <DATE>2018-03-28 21:32:54</DATE>
    <TEXT></TEXT>
    <INFO>Reddit post</INFO>
  </WRITING>
  <WRITING>
    <TITLE>Membrane=big gay</TITLE>
    <DATE>2018-03-28 22:07:41</DATE>
    <TEXT></TEXT>
    <INFO>Reddit post</INFO>
  </WRITING>
  <WRITING>
    <TITLE>This is getting out of hand, now there #8217;s two of them!</TITLE>
    <DATE>2018-04-02 06:53:55</DATE>
    <TEXT></TEXT>
    <INFO>Reddit post</INFO>
  </WRITING>
  <WRITING>
    <TITLE>Jesus Christ is ryzen today</TITLE>
    <DATE>2018-04-02 06:54:46</DATE>
    <TEXT></TEXT>
    <INFO>Reddit post</INFO>
  </WRITING>
  <WRITING>
    <TITLE>The real Jesus</TITLE>
    <DATE>2018-04-03 03:17:20</DATE>
    <TEXT></TEXT>
    <INFO>Reddit post</INFO>
  </WRITING>
  <WRITING>
    <TITLE>The loitering corner</TITLE>
    <DATE>2018-04-03 04:13:13</DATE>
    <TEXT></TEXT>
    <INFO>Reddit post</INFO>
  </WRITING>
  <WRITING>
    <TITLE></TITLE>
    <DATE>2018-04-03 04:21:37</DATE>
    <TEXT>What #8217;s the key? hint 1: DJ Kaled, hint 2: my neighborhood hint 3 no space</TEXT>
    <INFO>Reddit post</INFO>
  </WRITING>
  <WRITING>
    <TITLE>He has the high ground</TITLE>
    <DATE>2018-04-03 09:04:25</DATE>
    <TEXT></TEXT>
    <INFO>Reddit post</INFO>
  </WRITING>
  <WRITING>
    <TITLE></TITLE>
    <DATE>2018-04-03 16:01:14</DATE>
    <TEXT>One time, I ate a cheeseburger at the original cheeseburger in paradise in Hawaii</TEXT>
    <INFO>Reddit post</INFO>
  </WRITING>
  <WRITING>
    <TITLE></TITLE>
    <DATE>2018-04-03 16:02:27</DATE>
    <TEXT>I #8217;m a pretty kool kid</TEXT>
    <INFO>Reddit post</INFO>
  </WRITING>
  <WRITING>
    <TITLE></TITLE>
    <DATE>2018-04-03 20:30:41</DATE>
    <TEXT>Just look at the overwatch league, gaming is becoming more respected long before he unfortunate rise of fortnite</TEXT>
    <INFO>Reddit post</INFO>
  </WRITING>
  <WRITING>
    <TITLE></TITLE>
    <DATE>2018-04-03 20:36:32</DATE>
    <TEXT>Plot twist: iOS release</TEXT>
    <INFO>Reddit post</INFO>
  </WRITING>
  <WRITING>
    <TITLE>Change my mind</TITLE>
    <DATE>2018-04-04 15:13:43</DATE>
    <TEXT></TEXT>
    <INFO>Reddit post</INFO>
  </WRITING>
  <WRITING>
    <TITLE></TITLE>
    <DATE>2018-04-04 16:38:31</DATE>
    <TEXT>Ahh general reposti</TEXT>
    <INFO>Reddit post</INFO>
  </WRITING>
  <WRITING>
    <TITLE>What did you doing the Great War?</TITLE>
    <DATE>2018-04-05 16:36:25</DATE>
    <TEXT></TEXT>
    <INFO>Reddit post</INFO>
  </WRITING>
  <WRITING>
    <TITLE>Coding an autonomous</TITLE>
    <DATE>2018-04-05 18:28:34</DATE>
    <TEXT></TEXT>
    <INFO>Reddit post</INFO>
  </WRITING>
  <WRITING>
    <TITLE></TITLE>
    <DATE>2018-04-06 15:20:41</DATE>
    <TEXT>Ahhh general reposti!</TEXT>
    <INFO>Reddit post</INFO>
  </WRITING>
  <WRITING>
    <TITLE></TITLE>
    <DATE>2018-04-06 22:25:11</DATE>
    <TEXT>My lord, is this legal?</TEXT>
    <INFO>Reddit post</INFO>
  </WRITING>
  <WRITING>
    <TITLE></TITLE>
    <DATE>2018-04-07 05:06:53</DATE>
    <TEXT>I really want to major in film and tv production. My only worry is that I won #8217;t be able to make enough money to cover the cost of living in California (I live in Nebraska now)</TEXT>
    <INFO>Reddit post</INFO>
  </WRITING>
  <WRITING>
    <TITLE>It #8217;s free real estate</TITLE>
    <DATE>2018-04-08 07:23:24</DATE>
    <TEXT></TEXT>
    <INFO>Reddit post</INFO>
  </WRITING>
  <WRITING>
    <TITLE></TITLE>
    <DATE>2018-04-09 20:24:37</DATE>
    <TEXT>My lord, is this legal?</TEXT>
    <INFO>Reddit post</INFO>
  </WRITING>
  <WRITING>
    <TITLE>Potential new format?</TITLE>
    <DATE>2018-04-09 21:42:50</DATE>
    <TEXT></TEXT>
    <INFO>Reddit post</INFO>
  </WRITING>
  <WRITING>
    <TITLE>Membene= big gay</TITLE>
    <DATE>2018-04-14 16:06:31</DATE>
    <TEXT></TEXT>
    <INFO>Reddit post</INFO>
  </WRITING>
  <WRITING>
    <TITLE>When new mods are in town</TITLE>
    <DATE>2018-04-15 02:48:12</DATE>
    <TEXT></TEXT>
    <INFO>Reddit post</INFO>
  </WRITING>
  <WRITING>
    <TITLE></TITLE>
    <DATE>2018-04-15 15:48:11</DATE>
    <TEXT>This is proved by the RGB fan still sitting on the FRC material shelf...</TEXT>
    <INFO>Reddit post</INFO>
  </WRITING>
  <WRITING>
    <TITLE></TITLE>
    <DATE>2018-04-17 04:52:16</DATE>
    <TEXT>My lord, is this legal?</TEXT>
    <INFO>Reddit post</INFO>
  </WRITING>
  <WRITING>
    <TITLE></TITLE>
    <DATE>2018-04-18 05:32:18</DATE>
    <TEXT>r/imveryedgy</TEXT>
    <INFO>Reddit post</INFO>
  </WRITING>
  <WRITING>
    <TITLE>Depression is a disease</TITLE>
    <DATE>2018-04-18 15:43:27</DATE>
    <TEXT></TEXT>
    <INFO>Reddit post</INFO>
  </WRITING>
  <WRITING>
    <TITLE>Oh boy</TITLE>
    <DATE>2018-04-18 22:09:17</DATE>
    <TEXT></TEXT>
    <INFO>Reddit post</INFO>
  </WRITING>
  <WRITING>
    <TITLE>But I won #8217;t do that</TITLE>
    <DATE>2018-04-19 00:28:22</DATE>
    <TEXT></TEXT>
    <INFO>Reddit post</INFO>
  </WRITING>
  <WRITING>
    <TITLE>Onli-won cannoli</TITLE>
    <DATE>2018-04-23 04:04:42</DATE>
    <TEXT></TEXT>
    <INFO>Reddit post</INFO>
  </WRITING>
  <WRITING>
    <TITLE></TITLE>
    <DATE>2018-04-23 15:13:55</DATE>
    <TEXT>Engage</TEXT>
    <INFO>Reddit post</INFO>
  </WRITING>
  <WRITING>
    <TITLE>Format on the rise</TITLE>
    <DATE>2018-04-23 17:09:45</DATE>
    <TEXT></TEXT>
    <INFO>Reddit post</INFO>
  </WRITING>
  <WRITING>
    <TITLE></TITLE>
    <DATE>2018-04-23 19:52:29</DATE>
    <TEXT>Civilizations After spending weeks developing your empire, it #8217;s an amazing feeling to watch your rocket blast off for mars</TEXT>
    <INFO>Reddit post</INFO>
  </WRITING>
  <WRITING>
    <TITLE>I have a bad feeling about this</TITLE>
    <DATE>2018-04-24 19:32:18</DATE>
    <TEXT></TEXT>
    <INFO>Reddit post</INFO>
  </WRITING>
  <WRITING>
    <TITLE>Good times with Mr. Clark</TITLE>
    <DATE>2018-04-24 20:13:31</DATE>
    <TEXT></TEXT>
    <INFO>Reddit post</INFO>
  </WRITING>
  <WRITING>
    <TITLE>When people explain the prequel memes without subtitles in the title</TITLE>
    <DATE>2018-04-25 17:14:16</DATE>
    <TEXT></TEXT>
    <INFO>Reddit post</INFO>
  </WRITING>
  <WRITING>
    <TITLE>When you #8217;re a French chemist</TITLE>
    <DATE>2018-04-25 19:02:29</DATE>
    <TEXT></TEXT>
    <INFO>Reddit post</INFO>
  </WRITING>
  <WRITING>
    <TITLE>When Mr. Fisher sees your demerit card</TITLE>
    <DATE>2018-04-26 21:41:26</DATE>
    <TEXT></TEXT>
    <INFO>Reddit post</INFO>
  </WRITING>
  <WRITING>
    <TITLE>When you can see</TITLE>
    <DATE>2018-04-27 01:04:30</DATE>
    <TEXT></TEXT>
    <INFO>Reddit post</INFO>
  </WRITING>
  <WRITING>
    <TITLE></TITLE>
    <DATE>2018-04-28 15:31:10</DATE>
    <TEXT>You are a bold one</TEXT>
    <INFO>Reddit post</INFO>
  </WRITING>
  <WRITING>
    <TITLE>I #8217;m Rick Harrison, and this is my chin</TITLE>
    <DATE>2018-04-30 16:36:47</DATE>
    <TEXT></TEXT>
    <INFO>Reddit post</INFO>
  </WRITING>
  <WRITING>
    <TITLE>When you post OC, it gets reposted and people downvote you for reposting</TITLE>
    <DATE>2018-05-01 15:45:03</DATE>
    <TEXT></TEXT>
    <INFO>Reddit post</INFO>
  </WRITING>
  <WRITING>
    <TITLE>Gulag</TITLE>
    <DATE>2018-05-02 00:30:48</DATE>
    <TEXT></TEXT>
    <INFO>Reddit post</INFO>
  </WRITING>
  <WRITING>
    <TITLE></TITLE>
    <DATE>2018-05-02 18:11:16</DATE>
    <TEXT>r/deepfriedmemes</TEXT>
    <INFO>Reddit post</INFO>
  </WRITING>
  <WRITING>
    <TITLE>Ding dong</TITLE>
    <DATE>2018-05-02 18:13:04</DATE>
    <TEXT></TEXT>
    <INFO>Reddit post</INFO>
  </WRITING>
  <WRITING>
    <TITLE>Spotify made their song progress bar a lightsaber to celebrate Star Wars day</TITLE>
    <DATE>2018-05-04 20:29:06</DATE>
    <TEXT></TEXT>
    <INFO>Reddit post</INFO>
  </WRITING>
  <WRITING>
    <TITLE>I don #8217;t feel so good</TITLE>
    <DATE>2018-05-05 02:24:47</DATE>
    <TEXT></TEXT>
    <INFO>Reddit post</INFO>
  </WRITING>
  <WRITING>
    <TITLE></TITLE>
    <DATE>2018-05-06 06:45:11</DATE>
    <TEXT>Fatality</TEXT>
    <INFO>Reddit post</INFO>
  </WRITING>
  <WRITING>
    <TITLE></TITLE>
    <DATE>2018-05-06 18:21:32</DATE>
    <TEXT>I might be able to assist you</TEXT>
    <INFO>Reddit post</INFO>
  </WRITING>
  <WRITING>
    <TITLE>Discussion: Staff leaving Prep next year</TITLE>
    <DATE>2018-05-07 16:29:19</DATE>
    <TEXT>As many of you may know, many prominent members of the prep staff will be leaving next year, including Fr, Kroll, Fr. Went, and Mrs. Thompson. Please discuss below any memories or predictions for who will fill these roles next year.</TEXT>
    <INFO>Reddit post</INFO>
  </WRITING>
  <WRITING>
    <TITLE></TITLE>
    <DATE>2018-05-07 17:59:04</DATE>
    <TEXT>He seems like a pretty cool guy from his twitter profile, we #8217;ll see how he compares to Ryberg though.</TEXT>
    <INFO>Reddit post</INFO>
  </WRITING>
  <WRITING>
    <TITLE>I don #8217;t feel so good</TITLE>
    <DATE>2018-05-07 18:50:14</DATE>
    <TEXT></TEXT>
    <INFO>Reddit post</INFO>
  </WRITING>
  <WRITING>
    <TITLE>Why are you running?</TITLE>
    <DATE>2018-05-07 20:18:05</DATE>
    <TEXT></TEXT>
    <INFO>Reddit post</INFO>
  </WRITING>
  <WRITING>
    <TITLE></TITLE>
    <DATE>2018-05-07 21:37:29</DATE>
    <TEXT>General reposti</TEXT>
    <INFO>Reddit post</INFO>
  </WRITING>
  <WRITING>
    <TITLE></TITLE>
    <DATE>2018-05-08 02:12:17</DATE>
    <TEXT>@young_blk_giftd</TEXT>
    <INFO>Reddit post</INFO>
  </WRITING>
  <WRITING>
    <TITLE>And also with you</TITLE>
    <DATE>2018-05-11 15:32:34</DATE>
    <TEXT></TEXT>
    <INFO>Reddit post</INFO>
  </WRITING>
  <WRITING>
    <TITLE>I finally made the pilgrimage: (KC)</TITLE>
    <DATE>2018-05-12 22:32:32</DATE>
    <TEXT></TEXT>
    <INFO>Reddit post</INFO>
  </WRITING>
  <WRITING>
    <TITLE>We are lucky</TITLE>
    <DATE>2018-05-13 03:39:13</DATE>
    <TEXT></TEXT>
    <INFO>Reddit post</INFO>
  </WRITING>
  <WRITING>
    <TITLE>Me at the dentist</TITLE>
    <DATE>2018-05-13 20:09:24</DATE>
    <TEXT></TEXT>
    <INFO>Reddit post</INFO>
  </WRITING>
  <WRITING>
    <TITLE>No! Stop it!</TITLE>
    <DATE>2018-05-14 00:06:22</DATE>
    <TEXT></TEXT>
    <INFO>Reddit post</INFO>
  </WRITING>
  <WRITING>
    <TITLE></TITLE>
    <DATE>2018-05-15 04:57:45</DATE>
    <TEXT>But how did you KNOW it #8217;s a cat?</TEXT>
    <INFO>Reddit post</INFO>
  </WRITING>
  <WRITING>
    <TITLE>When you realize that Instagram accounts repost all of our memes</TITLE>
    <DATE>2018-05-15 19:24:34</DATE>
    <TEXT></TEXT>
    <INFO>Reddit post</INFO>
  </WRITING>
  <WRITING>
    <TITLE>When you chuckle at a meme but then see  #8220;general reposti #8221; in the comments</TITLE>
    <DATE>2018-05-16 03:46:57</DATE>
    <TEXT></TEXT>
    <INFO>Reddit post</INFO>
  </WRITING>
  <WRITING>
    <TITLE>Take a yeet young skywalker</TITLE>
    <DATE>2018-05-16 03:51:50</DATE>
    <TEXT></TEXT>
    <INFO>Reddit post</INFO>
  </WRITING>
  <WRITING>
    <TITLE>A brief reminder of the rules of this sub...</TITLE>
    <DATE>2018-05-16 21:45:34</DATE>
    <TEXT>Greetings everyone, Recently me and other members of the mod team have noticed a large influx of new users to this sub. Because of this, I am taking this opportunity to remind everyone of the rules. - No sharing answers or test questions - No over the top offensive humor -No doxing or other potentially harmful activities Note on memes: Everyone, (including the mod team) loves memes. We value the freedom of expression of Redditers and do our best to not intervene with most posts. We have noticed that memes on this sub commonly poke fun at teachers or specific members of the prep community. In our eyes, this is fine as long as the meme isn #8217;t overly offensive or over the top. We are big fans of freedom of speech and want to stay out of regulation as much as possible, but these rules will be enforced to avoid any problems with the administration. Thanks -The mod team</TEXT>
    <INFO>Reddit post</INFO>
  </WRITING>
  <WRITING>
    <TITLE></TITLE>
    <DATE>2018-05-17 19:23:57</DATE>
    <TEXT>Where should we drop off the items?</TEXT>
    <INFO>Reddit post</INFO>
  </WRITING>
  <WRITING>
    <TITLE></TITLE>
    <DATE>2018-05-17 22:14:35</DATE>
    <TEXT>This post has been removed for spam</TEXT>
    <INFO>Reddit post</INFO>
  </WRITING>
  <WRITING>
    <TITLE>When you #8217;re waiting for PowerSchool to load your grades after you refresh it</TITLE>
    <DATE>2018-05-18 17:31:58</DATE>
    <TEXT></TEXT>
    <INFO>Reddit post</INFO>
  </WRITING>
  <WRITING>
    <TITLE>When Siri can #8217;t understand what you #8217;re saying</TITLE>
    <DATE>2018-05-21 16:44:17</DATE>
    <TEXT></TEXT>
    <INFO>Reddit post</INFO>
  </WRITING>
  <WRITING>
    <TITLE></TITLE>
    <DATE>2018-05-21 17:05:39</DATE>
    <TEXT>It #8217;s treason then</TEXT>
    <INFO>Reddit post</INFO>
  </WRITING>
  <WRITING>
    <TITLE></TITLE>
    <DATE>2018-05-21 18:38:18</DATE>
    <TEXT>General reposti</TEXT>
    <INFO>Reddit post</INFO>
  </WRITING>
  <WRITING>
    <TITLE></TITLE>
    <DATE>2018-05-21 18:54:20</DATE>
    <TEXT>Someone posted exactly this 4 hours ago</TEXT>
    <INFO>Reddit post</INFO>
  </WRITING>
  <WRITING>
    <TITLE></TITLE>
    <DATE>2018-05-22 02:19:41</DATE>
    <TEXT>You forgot the part where he lit their tails on fire and let them run through the fields of Israels #8217; enemy</TEXT>
    <INFO>Reddit post</INFO>
  </WRITING>
  <WRITING>
    <TITLE></TITLE>
    <DATE>2018-05-23 04:29:50</DATE>
    <TEXT>It #8217;s treason then</TEXT>
    <INFO>Reddit post</INFO>
  </WRITING>
  <WRITING>
    <TITLE></TITLE>
    <DATE>2018-05-23 04:33:34</DATE>
    <TEXT>Merchant of Venice- Antonio lives</TEXT>
    <INFO>Reddit post</INFO>
  </WRITING>
  <WRITING>
    <TITLE></TITLE>
    <DATE>2018-05-23 04:34:33</DATE>
    <TEXT>You #8217;re thinking of Bassanio, Antonio never got married, at least from what I remember ;)</TEXT>
    <INFO>Reddit post</INFO>
  </WRITING>
  <WRITING>
    <TITLE></TITLE>
    <DATE>2018-05-23 04:35:51</DATE>
    <TEXT>This is getting out of hand</TEXT>
    <INFO>Reddit post</INFO>
  </WRITING>
  <WRITING>
    <TITLE></TITLE>
    <DATE>2018-05-23 04:56:40</DATE>
    <TEXT>Take a seat young Skywalker</TEXT>
    <INFO>Reddit post</INFO>
  </WRITING>
  <WRITING>
    <TITLE>Melon man, defender of the vine</TITLE>
    <DATE>2018-05-24 00:55:24</DATE>
    <TEXT></TEXT>
    <INFO>Reddit post</INFO>
  </WRITING>
  <WRITING>
    <TITLE></TITLE>
    <DATE>2018-05-25 07:26:31</DATE>
    <TEXT>Yes</TEXT>
    <INFO>Reddit post</INFO>
  </WRITING>
  <WRITING>
    <TITLE></TITLE>
    <DATE>2018-05-26 23:57:54</DATE>
    <TEXT>It #8217;s always on channel 7... now I watch fox 42</TEXT>
    <INFO>Reddit post</INFO>
  </WRITING>
  <WRITING>
    <TITLE></TITLE>
    <DATE>2018-06-02 18:38:27</DATE>
    <TEXT>r/fakehistoryporn</TEXT>
    <INFO>Reddit post</INFO>
  </WRITING>
  <WRITING>
    <TITLE></TITLE>
    <DATE>2018-06-05 19:42:48</DATE>
    <TEXT>Are you thinking of Petros?</TEXT>
    <INFO>Reddit post</INFO>
  </WRITING>
  <WRITING>
    <TITLE>When your friend is about to step in dog poop</TITLE>
    <DATE>2018-06-05 22:19:48</DATE>
    <TEXT></TEXT>
    <INFO>Reddit post</INFO>
  </WRITING>
  <WRITING>
    <TITLE>What is the biggest design flaw of the human body?</TITLE>
    <DATE>2018-06-06 01:23:09</DATE>
    <TEXT></TEXT>
    <INFO>Reddit post</INFO>
  </WRITING>
  <WRITING>
    <TITLE></TITLE>
    <DATE>2018-06-06 01:31:37</DATE>
    <TEXT>Personally the tax cuts have been my favorite, wasn #8217;t expecting Trump to be so conservative policy wise but I was pleasantly surprised.</TEXT>
    <INFO>Reddit post</INFO>
  </WRITING>
  <WRITING>
    <TITLE></TITLE>
    <DATE>2018-06-06 01:31:57</DATE>
    <TEXT>Fahrenheit 451</TEXT>
    <INFO>Reddit post</INFO>
  </WRITING>
  <WRITING>
    <TITLE></TITLE>
    <DATE>2018-06-06 01:34:50</DATE>
    <TEXT>I #8217;ve always wondered about this! Why not go through puberty way earlier so you can get your  #8220;punk years #8221; out of the way at like 6</TEXT>
    <INFO>Reddit post</INFO>
  </WRITING>
  <WRITING>
    <TITLE></TITLE>
    <DATE>2018-06-06 01:59:35</DATE>
    <TEXT>Actually my mortgage has gone down $132 a month! As for my job, how will more revenue at the top put it in jeopardy....?</TEXT>
    <INFO>Reddit post</INFO>
  </WRITING>
  <WRITING>
    <TITLE></TITLE>
    <DATE>2018-06-06 02:06:03</DATE>
    <TEXT>Well, out here in the Midwest things couldn #8217;t be going better. Average income has been on a steady rise for the last 7 months, life is good, and as for tax cuts destroying the value of the dollar, could you explain that a bit more? I don #8217;t quite understand how more money in everyone #8217;s pocket would do that.</TEXT>
    <INFO>Reddit post</INFO>
  </WRITING>
  <WRITING>
    <TITLE></TITLE>
    <DATE>2018-06-06 02:15:37</DATE>
    <TEXT>People giving less money to the government is theft? I would argue the opposite. What kind of thief lowers their demands?</TEXT>
    <INFO>Reddit post</INFO>
  </WRITING>
  <WRITING>
    <TITLE></TITLE>
    <DATE>2018-06-06 02:32:55</DATE>
    <TEXT>But under free market capitalism prices naturally go down due to competition. (-shortages/inflation). Higher taxes in reality cause businesses to raise prices as a larger chunk of their profits are taken by the government. Edit: spelling</TEXT>
    <INFO>Reddit post</INFO>
  </WRITING>
  <WRITING>
    <TITLE>Me #127794;irl</TITLE>
    <DATE>2018-06-07 03:49:17</DATE>
    <TEXT></TEXT>
    <INFO>Reddit post</INFO>
  </WRITING>
  <WRITING>
    <TITLE>GF #128056; or BF #128056;</TITLE>
    <DATE>2018-06-07 03:55:17</DATE>
    <TEXT></TEXT>
    <INFO>Reddit post</INFO>
  </WRITING>
  <WRITING>
    <TITLE>The true meaning of E3</TITLE>
    <DATE>2018-06-08 14:40:20</DATE>
    <TEXT></TEXT>
    <INFO>Reddit post</INFO>
  </WRITING>
  <WRITING>
    <TITLE></TITLE>
    <DATE>2018-06-08 16:10:44</DATE>
    <TEXT>General reposti!</TEXT>
    <INFO>Reddit post</INFO>
  </WRITING>
  <WRITING>
    <TITLE></TITLE>
    <DATE>2018-06-08 16:17:54</DATE>
    <TEXT>r/fakehistoryporn</TEXT>
    <INFO>Reddit post</INFO>
  </WRITING>
  <WRITING>
    <TITLE></TITLE>
    <DATE>2018-06-08 16:22:27</DATE>
    <TEXT>General reposti!</TEXT>
    <INFO>Reddit post</INFO>
  </WRITING>
  <WRITING>
    <TITLE></TITLE>
    <DATE>2018-06-08 16:34:31</DATE>
    <TEXT>CS:GO- people who are good are accused of aimbotting pretty frequently</TEXT>
    <INFO>Reddit post</INFO>
  </WRITING>
  <WRITING>
    <TITLE></TITLE>
    <DATE>2018-06-12 04:06:24</DATE>
    <TEXT>You #8217;re subbed to r/sequelmemes : it #8217;s treason then</TEXT>
    <INFO>Reddit post</INFO>
  </WRITING>
  <WRITING>
    <TITLE>(2018 colorized)</TITLE>
    <DATE>2018-06-12 19:17:50</DATE>
    <TEXT></TEXT>
    <INFO>Reddit post</INFO>
  </WRITING>
  <WRITING>
    <TITLE></TITLE>
    <DATE>2018-06-17 01:39:40</DATE>
    <TEXT>When your parents check PowerSchool</TEXT>
    <INFO>Reddit post</INFO>
  </WRITING>
  <WRITING>
    <TITLE>From r/memes</TITLE>
    <DATE>2018-06-28 19:10:54</DATE>
    <TEXT></TEXT>
    <INFO>Reddit post</INFO>
  </WRITING>
  <WRITING>
    <TITLE></TITLE>
    <DATE>2018-06-28 20:40:39</DATE>
    <TEXT>TO THE PLAAAAAAACE</TEXT>
    <INFO>Reddit post</INFO>
  </WRITING>
  <WRITING>
    <TITLE></TITLE>
    <DATE>2018-06-29 04:48:57</DATE>
    <TEXT>r/dankchristianmemes</TEXT>
    <INFO>Reddit post</INFO>
  </WRITING>
  <WRITING>
    <TITLE>The next stage of evolution</TITLE>
    <DATE>2018-07-01 16:06:13</DATE>
    <TEXT></TEXT>
    <INFO>Reddit post</INFO>
  </WRITING>
  <WRITING>
    <TITLE></TITLE>
    <DATE>2018-07-01 16:07:55</DATE>
    <TEXT>But it #8217;s not corn</TEXT>
    <INFO>Reddit post</INFO>
  </WRITING>
  <WRITING>
    <TITLE>When someone downvotes a corn meme</TITLE>
    <DATE>2018-07-01 16:27:22</DATE>
    <TEXT></TEXT>
    <INFO>Reddit post</INFO>
  </WRITING>
  <WRITING>
    <TITLE></TITLE>
    <DATE>2018-07-01 19:37:15</DATE>
    <TEXT>GBR</TEXT>
    <INFO>Reddit post</INFO>
  </WRITING>
  <WRITING>
    <TITLE></TITLE>
    <DATE>2018-07-03 17:03:25</DATE>
    <TEXT>I #8217;ve got a stuffed Perry the Platypus plushie next to my bed to this day</TEXT>
    <INFO>Reddit post</INFO>
  </WRITING>
  <WRITING>
    <TITLE></TITLE>
    <DATE>2018-07-03 21:12:47</DATE>
    <TEXT>P</TEXT>
    <INFO>Reddit post</INFO>
  </WRITING>
  <WRITING>
    <TITLE></TITLE>
    <DATE>2018-07-03 21:13:58</DATE>
    <TEXT>O</TEXT>
    <INFO>Reddit post</INFO>
  </WRITING>
  <WRITING>
    <TITLE></TITLE>
    <DATE>2018-07-03 21:14:33</DATE>
    <TEXT>I</TEXT>
    <INFO>Reddit post</INFO>
  </WRITING>
  <WRITING>
    <TITLE>Richard, how could you _______? It #8217;s tearing the family apart!</TITLE>
    <DATE>2018-07-03 21:16:22</DATE>
    <TEXT></TEXT>
    <INFO>Reddit post</INFO>
  </WRITING>
  <WRITING>
    <TITLE></TITLE>
    <DATE>2018-07-03 21:16:51</DATE>
    <TEXT>I</TEXT>
    <INFO>Reddit post</INFO>
  </WRITING>
  <WRITING>
    <TITLE></TITLE>
    <DATE>2018-07-11 04:19:45</DATE>
    <TEXT>Frog and Toad is a goldmine</TEXT>
    <INFO>Reddit post</INFO>
  </WRITING>
  <WRITING>
    <TITLE></TITLE>
    <DATE>2018-07-11 19:48:44</DATE>
    <TEXT>Sam O #8217; Nella</TEXT>
    <INFO>Reddit post</INFO>
  </WRITING>
  <WRITING>
    <TITLE>But isn #8217;t socialism left-wing? #129300;</TITLE>
    <DATE>2018-07-17 03:32:53</DATE>
    <TEXT></TEXT>
    <INFO>Reddit post</INFO>
  </WRITING>
  <WRITING>
    <TITLE></TITLE>
    <DATE>2018-07-17 03:57:00</DATE>
    <TEXT>This is correct, I figured the message was self evident. Apologies</TEXT>
    <INFO>Reddit post</INFO>
  </WRITING>
  <WRITING>
    <TITLE></TITLE>
    <DATE>2018-07-17 04:25:32</DATE>
    <TEXT>Not quite. socialism is the economic policy of equality for all while fascism relies on a top-down authoritarian state. You can learn more here: https://www.diffen.com/difference/Communism_vs_Fascism</TEXT>
    <INFO>Reddit post</INFO>
  </WRITING>
  <WRITING>
    <TITLE>I got time</TITLE>
    <DATE>2018-07-17 12:54:09</DATE>
    <TEXT></TEXT>
    <INFO>Reddit post</INFO>
  </WRITING>
  <WRITING>
    <TITLE></TITLE>
    <DATE>2018-07-17 16:21:12</DATE>
    <TEXT>Time? Yes, I have it.</TEXT>
    <INFO>Reddit post</INFO>
  </WRITING>
  <WRITING>
    <TITLE>Well of course I know him, he #8217;s me</TITLE>
    <DATE>2018-07-17 16:29:41</DATE>
    <TEXT></TEXT>
    <INFO>Reddit post</INFO>
  </WRITING>
  <WRITING>
    <TITLE>Lol gae</TITLE>
    <DATE>2018-07-19 21:15:10</DATE>
    <TEXT></TEXT>
    <INFO>Reddit post</INFO>
  </WRITING>
  <WRITING>
    <TITLE></TITLE>
    <DATE>2018-07-19 22:15:38</DATE>
    <TEXT>L</TEXT>
    <INFO>Reddit post</INFO>
  </WRITING>
  <WRITING>
    <TITLE></TITLE>
    <DATE>2018-07-19 22:16:03</DATE>
    <TEXT>Y</TEXT>
    <INFO>Reddit post</INFO>
  </WRITING>
  <WRITING>
    <TITLE>Your mum _______, lol</TITLE>
    <DATE>2018-07-19 22:17:49</DATE>
    <TEXT></TEXT>
    <INFO>Reddit post</INFO>
  </WRITING>
  <WRITING>
    <TITLE></TITLE>
    <DATE>2018-07-19 22:18:03</DATE>
    <TEXT>R</TEXT>
    <INFO>Reddit post</INFO>
  </WRITING>
  <WRITING>
    <TITLE>The secret they #8217;ve been keeping from us</TITLE>
    <DATE>2018-07-20 18:42:45</DATE>
    <TEXT></TEXT>
    <INFO>Reddit post</INFO>
  </WRITING>
  <WRITING>
    <TITLE>The big secret</TITLE>
    <DATE>2018-07-20 18:53:18</DATE>
    <TEXT></TEXT>
    <INFO>Reddit post</INFO>
  </WRITING>
  <WRITING>
    <TITLE>This format is rising, all in!!!</TITLE>
    <DATE>2018-07-20 18:54:50</DATE>
    <TEXT></TEXT>
    <INFO>Reddit post</INFO>
  </WRITING>
  <WRITING>
    <TITLE></TITLE>
    <DATE>2018-07-20 21:46:15</DATE>
    <TEXT>Gucci Gang</TEXT>
    <INFO>Reddit post</INFO>
  </WRITING>
  <WRITING>
    <TITLE>CMV: Reddit #8217;s upvote/downvote system discourages sharing unpopular opinions</TITLE>
    <DATE>2018-07-20 22:14:14</DATE>
    <TEXT>Reddit #8217;s upvote/downvote system; while very good at bringing us the best in adorable pets and funny GIFs, it seems to discourage the free flow of ideas and can entirely shit down fringe opinions. Take for example political subreddits. Say someone posts a comment that the majority of people disagree with. The instinctive response of the people who disagree with the comment is to downvote it. This has two effects, both of which discourage people from sharing new ideas. The first is that because it is downvoted so much, the comment is quickly buried and few people get so see it. The second is that it looses the commenter karma, discouraging them from going against the majority in the future. I #8217;m not sure how Thai problem could be solved but I #8217;m excited to see your responses. :)</TEXT>
    <INFO>Reddit post</INFO>
  </WRITING>
  <WRITING>
    <TITLE></TITLE>
    <DATE>2018-07-20 23:06:20</DATE>
    <TEXT> #916; What struck me the most about this response is that by down voting people are expressing their opinion as well, which is something I hadn't considered. However, my main concern is the fact that entire narratives can be buried by this. It is true that with so many subs out there its difficult for it to be truly buried, but this sort of thing can (and does) turn many subs into echo chambers.</TEXT>
    <INFO>Reddit post</INFO>
  </WRITING>
  <WRITING>
    <TITLE></TITLE>
    <DATE>2018-07-20 23:11:23</DATE>
    <TEXT>In most cases I think the filtering does its job. (see my example of adorable pets in the original post). My problem comes in cases where entire narratives (specifically political) can be buried. I don't think Reddit's purpose is to equally express all opinions(as all opinions are not equal) but I think its important that it not turn into an echo chamber</TEXT>
    <INFO>Reddit post</INFO>
  </WRITING>
  <WRITING>
    <TITLE></TITLE>
    <DATE>2018-07-20 23:19:28</DATE>
    <TEXT>(My response is similar to the ones above, look there for a more detailed explanation) It's not so much the backlash that a post or comment has that I'm concerned with. More that it can be buried rather quickly which in some cases leads to an impenetrable echo chamber effect.</TEXT>
    <INFO>Reddit post</INFO>
  </WRITING>
  <WRITING>
    <TITLE></TITLE>
    <DATE>2018-07-21 15:38:24</DATE>
    <TEXT>REEEEEEEEEEEEEE</TEXT>
    <INFO>Reddit post</INFO>
  </WRITING>
  <WRITING>
    <TITLE></TITLE>
    <DATE>2018-07-22 05:06:38</DATE>
    <TEXT>I will argue this with a religious freedom angle- Because circumcision is and has been commonplace for Jews and Christians for literally thousands of years. Even if you exclude the obvious health benefits and traditional value, the idea that it #8217;s the government #8217;s place to stop a religious right of passage is asinine.</TEXT>
    <INFO>Reddit post</INFO>
  </WRITING>
  <WRITING>
    <TITLE></TITLE>
    <DATE>2018-07-22 05:20:40</DATE>
    <TEXT>I #8217;m going to argue this through the Darwinian perspective of biology and exclude the psychology( in my opinion that #8217;s where the root of transgenderism lies) For most of the history of life on earth there has been a relatively consistent archetype of mother and father coming together to form a child. This has been the case for millions of years. This simple concept really seems to rip the scientific case for transgenderism apart. If it #8217;s the case that that someone can be a man in a woman #8217;s body (or vise versa) You would have to undermine millions of years of evolutionary history, not to mention the entire concept of sexual selection. If most women prefer men and most men prefer women, explain to me how a genetic abnormality such as transgenderism could be allowed to survive?</TEXT>
    <INFO>Reddit post</INFO>
  </WRITING>
  <WRITING>
    <TITLE></TITLE>
    <DATE>2018-07-22 05:25:50</DATE>
    <TEXT>My point is that it #8217;s not the governments job to interfere with a relatively harmless and beneficial ritual. However, I think I see where you #8217;re trying to go with this. On the case of the female general mutilation, I would argue that in most cases it #8217;s used as a punishment for infidelity whereas circumsicion was never about that. You could also argue that circumsicion doesn #8217;t prevent the ability to bear children, it is simply a way to show ones identity as a Jew or Christian.</TEXT>
    <INFO>Reddit post</INFO>
  </WRITING>
  <WRITING>
    <TITLE></TITLE>
    <DATE>2018-07-22 05:32:27</DATE>
    <TEXT>Sure but those people are called intersex and make up a tiny percentage of the trans population. In their case I would accept either gender as it is biologically unclear(however the genitals would be an easy way to decide). I think the point here is that for the average Joe who is XY and has a penis, there is no biological argument you can make that could lead you to the idea that he is female.</TEXT>
    <INFO>Reddit post</INFO>
  </WRITING>
  <WRITING>
    <TITLE></TITLE>
    <DATE>2018-07-22 05:44:42</DATE>
    <TEXT>Wow. I #8217;m gonna need to reconsider this :) The point I was trying to refute was that transgenderism is somehow genetic( which I layed out above) I still think this point stands, but you are correct in the fact that this doesn #8217;t make transgenderism a non-issue. I think evolutionary biology suggests that transgenderism is a mental disorder that some personality types are most prone to than others. As for treatment, well, I haven #8217;t thought that through enough to give a coherent answer. Thanks for helping me learn more about this topic :)</TEXT>
    <INFO>Reddit post</INFO>
  </WRITING>
  <WRITING>
    <TITLE></TITLE>
    <DATE>2018-07-22 05:47:24</DATE>
    <TEXT>So in this case would the hypothetical woman #8217;s book club be  #8220;looking the other way #8221; on the science?</TEXT>
    <INFO>Reddit post</INFO>
  </WRITING>
  <WRITING>
    <TITLE></TITLE>
    <DATE>2018-07-22 05:56:21</DATE>
    <TEXT>It seems like the devil is in the details on this one. Who gets to decide when nudity is being used for just  #8220;shock power #8221; rather than  #8220;self expression #8221; . And even then, is there really a difference between the two? Personally if I see a naked dude on street, weather or not he #8217;s  #8220;expressing himself #8221; doesn #8217;t matter to me. I just don #8217;t want to see that.</TEXT>
    <INFO>Reddit post</INFO>
  </WRITING>
  <WRITING>
    <TITLE>Welcome u/CalColossus to the Moderation Team!</TITLE>
    <DATE>2018-07-24 02:25:26</DATE>
    <TEXT>After many months of extensive surveillance, research, and deliberation, the Moderation Team has selected u/CalColossus to join us going into the start of the 2018-2019 school year. We have great trust in his abilities and believe he will do an excellent job. Thank you to all who applied; we will reopen mod submissions at a later date.</TEXT>
    <INFO>Reddit post</INFO>
  </WRITING>
  <WRITING>
    <TITLE>Electron #128079; Configuration #128079;</TITLE>
    <DATE>2018-07-24 14:57:24</DATE>
    <TEXT></TEXT>
    <INFO>Reddit post</INFO>
  </WRITING>
  <WRITING>
    <TITLE>Perfectly balanced....</TITLE>
    <DATE>2018-07-24 22:16:10</DATE>
    <TEXT></TEXT>
    <INFO>Reddit post</INFO>
  </WRITING>
  <WRITING>
    <TITLE>Pretty versatile, some editing skills required</TITLE>
    <DATE>2018-07-29 19:34:06</DATE>
    <TEXT></TEXT>
    <INFO>Reddit post</INFO>
  </WRITING>
  <WRITING>
    <TITLE></TITLE>
    <DATE>2018-07-31 00:21:06</DATE>
    <TEXT>Nebraska-Corn, Trains, and Warren Buffet</TEXT>
    <INFO>Reddit post</INFO>
  </WRITING>
  <WRITING>
    <TITLE>People who voted for Hillary Clinton: what #8217;s one thing Trump has done that you agree with? [Serious]</TITLE>
    <DATE>2018-07-31 00:47:45</DATE>
    <TEXT></TEXT>
    <INFO>Reddit post</INFO>
  </WRITING>
  <WRITING>
    <TITLE></TITLE>
    <DATE>2018-07-31 00:58:15</DATE>
    <TEXT>And of course the occasional cow</TEXT>
    <INFO>Reddit post</INFO>
  </WRITING>
  <WRITING>
    <TITLE>The Sun bleached part the paint on my fooseball table</TITLE>
    <DATE>2018-07-31 18:19:22</DATE>
    <TEXT></TEXT>
    <INFO>Reddit post</INFO>
  </WRITING>
  <WRITING>
    <TITLE></TITLE>
    <DATE>2018-08-03 23:38:17</DATE>
    <TEXT>Graphics Cards in the PC building community</TEXT>
    <INFO>Reddit post</INFO>
  </WRITING>
  <WRITING>
    <TITLE>Beautiful</TITLE>
    <DATE>2018-08-04 16:22:25</DATE>
    <TEXT></TEXT>
    <INFO>Reddit post</INFO>
  </WRITING>
  <WRITING>
    <TITLE>T #128079;P #128079;O #128079;S #128079;E #128079;</TITLE>
    <DATE>2018-08-04 16:29:22</DATE>
    <TEXT></TEXT>
    <INFO>Reddit post</INFO>
  </WRITING>
  <WRITING>
    <TITLE>Superior intellect</TITLE>
    <DATE>2018-08-04 19:27:03</DATE>
    <TEXT></TEXT>
    <INFO>Reddit post</INFO>
  </WRITING>
  <WRITING>
    <TITLE></TITLE>
    <DATE>2018-08-05 01:34:36</DATE>
    <TEXT>What the fuck did you just fucking say about me, you little bitch? I'll have you know I graduated top of my class in the Navy Seals, and I've been involved in numerous secret raids on Al-Quaeda, and I have over 300 confirmed kills. I am trained in gorilla warfare and I'm the top sniper in the entire US armed forces. You are nothing to me but just another target. I will wipe you the fuck out with precision the likes of which has never been seen before on this Earth, mark my fucking words. You think you can get away with saying that shit to me over the Internet? Think again, fucker. As we speak I am contacting my secret network of spies across the USA and your IP is being traced right now so you better prepare for the storm, maggot. The storm that wipes out the pathetic little thing you call your life. You're fucking dead, kid. I can be anywhere, anytime, and I can kill you in over seven hundred ways, and that's just with my bare hands. Not only am I extensively trained in unarmed combat, but I have access to the entire arsenal of the United States Marine Corps and I will use it to its full extent to wipe your miserable ass off the face of the continent, you little shit. If only you could have known what unholy retribution your little "clever" comment was about to bring down upon you, maybe you would have held your fucking tongue. But you couldn't, you didn't, and now you're paying the price, you goddamn idiot. I will shit fury all over you and you will drown in it. You're fucking dead, kiddo.</TEXT>
    <INFO>Reddit post</INFO>
  </WRITING>
  <WRITING>
    <TITLE></TITLE>
    <DATE>2018-08-05 01:48:39</DATE>
    <TEXT>Many people always ask me how I was able to get into Harvard as a 16 year old who skipped 3 grades of high school. They think I got in because of my scholarly records, but no the key is the interview. As I sat in the Harvard Dean's office in front of the board of reviewers for my application, the Dean asks me "Why should you be a good candidate for this school?" They seemed bored but I replied "Well I was born a child prodigy, placed 1st in my state spelling bee for three consecutive years, I can speak eight different languages not counting Latin, play four different instruments, I skipped grades 4 through 6, and graduated my high school as valedictorian at the age of 14. I then worked as an intern at both Telsa, and NASA." Suddenly the room burst into laughter and many of board instantly started scribbling down "No" near the application check marks. The Dean says "Sorry but you are just not the type we are looking for." But then I said "Excuse me but I wasn't finished... I watch Rick and Morty" The Dean looked at me like an idiot and said "So....?" Then I replied with a smile "And I understand all the references and subtle jokes" An audible gasp let out by the board was so loud the secretary had to come in. You could hear a pin drop and then suddenly all at once the entire board clicked their pens on the "Approved Box" and I was instantly handed a diploma and now I'm teaching advanced physicals there. I guess you can say I'm pretty smart. :)</TEXT>
    <INFO>Reddit post</INFO>
  </WRITING>
  <WRITING>
    <TITLE></TITLE>
    <DATE>2018-08-05 01:51:13</DATE>
    <TEXT>What the fuck did you just fucking say about me, you little bitch? I'll have you know I graduated top of my class in the Navy Seals, and I've been involved in numerous secret raids on Al-Quaeda, and I have over 300 confirmed kills. I am trained in gorilla warfare and I'm the top sniper in the entire US armed forces. You are nothing to me but just another target. I will wipe you the fuck out with precision the likes of which has never been seen before on this Earth, mark my fucking words. You think you can get away with saying that shit to me over the Internet? Think again, fucker. As we speak I am contacting my secret network of spies across the USA and your IP is being traced right now so you better prepare for the storm, maggot. The storm that wipes out the pathetic little thing you call your life. You're fucking dead, kid. I can be anywhere, anytime, and I can kill you in over seven hundred ways, and that's just with my bare hands. Not only am I extensively trained in unarmed combat, but I have access to the entire arsenal of the United States Marine Corps and I will use it to its full extent to wipe your miserable ass off the face of the continent, you little shit. If only you could have known what unholy retribution your little "clever" comment was about to bring down upon you, maybe you would have held your fucking tongue. But you couldn't, you didn't, and now you're paying the price, you goddamn idiot. I will shit fury all over you and you will drown in it. You're fucking dead, kiddo.</TEXT>
    <INFO>Reddit post</INFO>
  </WRITING>
  <WRITING>
    <TITLE></TITLE>
    <DATE>2018-08-05 02:06:55</DATE>
    <TEXT>This isn #8217;t the whole song</TEXT>
    <INFO>Reddit post</INFO>
  </WRITING>
  <WRITING>
    <TITLE>Twitter today:</TITLE>
    <DATE>2018-08-05 02:26:17</DATE>
    <TEXT></TEXT>
    <INFO>Reddit post</INFO>
  </WRITING>
  <WRITING>
    <TITLE></TITLE>
    <DATE>2018-08-06 04:17:29</DATE>
    <TEXT>I posted this a week ago faggot</TEXT>
    <INFO>Reddit post</INFO>
  </WRITING>
  <WRITING>
    <TITLE>Of course I am!</TITLE>
    <DATE>2018-08-07 04:00:04</DATE>
    <TEXT></TEXT>
    <INFO>Reddit post</INFO>
  </WRITING>
  <WRITING>
    <TITLE>Of course I am!</TITLE>
    <DATE>2018-08-07 04:30:00</DATE>
    <TEXT></TEXT>
    <INFO>Reddit post</INFO>
  </WRITING>
  <WRITING>
    <TITLE></TITLE>
    <DATE>2018-08-07 05:35:38</DATE>
    <TEXT>Great minds think alike</TEXT>
    <INFO>Reddit post</INFO>
  </WRITING>
  <WRITING>
    <TITLE>Next week bois</TITLE>
    <DATE>2018-08-20 03:41:16</DATE>
    <TEXT></TEXT>
    <INFO>Reddit post</INFO>
  </WRITING>
  <WRITING>
    <TITLE>Thanks for the memories</TITLE>
    <DATE>2018-08-22 05:26:37</DATE>
    <TEXT></TEXT>
    <INFO>Reddit post</INFO>
  </WRITING>
  <WRITING>
    <TITLE>Final Score: 12-5 Prep</TITLE>
    <DATE>2018-08-24 05:50:34</DATE>
    <TEXT></TEXT>
    <INFO>Reddit post</INFO>
  </WRITING>
  <WRITING>
    <TITLE></TITLE>
    <DATE>2018-08-24 18:07:59</DATE>
    <TEXT>I was half asleep, forgive my transgressions</TEXT>
    <INFO>Reddit post</INFO>
  </WRITING>
  <WRITING>
    <TITLE></TITLE>
    <DATE>2018-08-28 04:38:24</DATE>
    <TEXT>Mods asleep: upvote sterling</TEXT>
    <INFO>Reddit post</INFO>
  </WRITING>
  <WRITING>
    <TITLE>Formal Dress Day: 8/28/18</TITLE>
    <DATE>2018-08-28 04:39:25</DATE>
    <TEXT></TEXT>
    <INFO>Reddit post</INFO>
  </WRITING>
  <WRITING>
    <TITLE></TITLE>
    <DATE>2018-08-30 19:55:51</DATE>
    <TEXT>Removed for rule 3</TEXT>
    <INFO>Reddit post</INFO>
  </WRITING>
  <WRITING>
    <TITLE>Eminem releases  #8220;Kamikaze #8221; (2018)</TITLE>
    <DATE>2018-09-03 02:30:38</DATE>
    <TEXT></TEXT>
    <INFO>Reddit post</INFO>
  </WRITING>
  </INDIVIDUAL>