<INDIVIDUAL>
  <ID>subject6309</ID>
  <WRITING>
    <TITLE>This is seriously messed up</TITLE>
    <DATE>2017-10-30 16:15:31</DATE>
    <TEXT></TEXT>
    <INFO>Reddit post</INFO>
  </WRITING>
  <WRITING>
    <TITLE></TITLE>
    <DATE>2017-10-31 09:10:39</DATE>
    <TEXT>So is $71.7 #795;9 #162; #808;  #1161;e #821; #833;q #808; #847;u #865;a #824; #823; #864;l #860; #856;  #823;t #824; #802;o #860; 7 #859; #785; #784; #860; #818; #819; #818; #797; #803;1 #838; #871; #877; #814; #804;7 #843; #838; #783; #877; #857; #813;9 #788; #842; #878; #769; #856; #814;  #867; #838; #838; #866;c #782; #864; #803; #854; #804; #825; #841; #803;e #835; #807; #806;n #871; #769; #813; #805; #792; #809; #812; #846; #852;t #849;s #876; #878; #844; #867; #779; #801; #811;  #770; #782; #781; #769; #876; #856; #812; #825; #854; #793; #796; #853; #819; #826; #816;o #788; #877; #834; #869; #831; #847; #801; #853; #826;r #830; #780; #786; #784; #870; #776; #801; #847; #789; #827; #819; #826;  #774; #784; #786; #868; #779; #772; #876; #785; #805; #811; #825; #852; #796; #792; #828; #810;7 #835; #776; #877; #774; #789; #861; #809; #812; #803; #818; #792; #809;1 #786; #779; #768; #879; #843; #835; #768; #844; #862; #841; #800; #846; #803; #837;. #773; #770; #781; #808; #791; #813; #837; #839; #845; #804; #791; #826; #851;. #855; #778; #787; #769; #869; #842; #843; #849; #782; #802; #832; #845; #793; #840; #793; #845; #800; #803; #853; #796; #853; #803; #857; #798; #809; #803;7 #848; #875; #878; #772; #877; #849; #868; #867; #788; #831; #769; #1161; #789; #796; #815; #813; #810; #798; #853; #814; #845; #837; #803; #813; #854; #797; #812;9 #772; #867; #878; #838; #771; #773; #770; #829; #787; #823; #821; #860; #801; #861; #854; #825; #814; #791; #790; #791; #800; #791; #793; #793;  #878; #769; #829; #875; #829; #876; #879; #834; #821; #847; #858; #806; #826; #814; #811;c #850; #873; #849; #855; #859; #783; #873; #844; #777; #768; #769; #867; #838; #834; #780; #789; #822; #866; #800; #825; #852; #846; #818; #815; #854;e #773; #834; #778; #783; #783; #788; #864; #790; #851; #846; #857; #800; #837;n #768; #876; #871; #873; #794; #784; #838; #844; #771; #769; #879; #876; #784; #787; #771; #786; #878; #833; #792; #796; #803; #839; #839; #840; #839; #800; #799; #793;t #868; #776; #782; #859; #848; #777; #836; #787; #781; #831; #768; #855; #874; #769; #821; #808; #826; #793; #840; #799; #857; #837; #812; #827; #792; #827; #827; #826; #826; #793; #827;s #871; #784; #838; #794; #778; #775; #786; #787; #842; #831; #777; #869; #772; #780; #869; #849; #874; #855; #808; #807; #813; #827; #811; #837; #845; #851; #854;</TEXT>
    <INFO>Reddit post</INFO>
  </WRITING>
  <WRITING>
    <TITLE></TITLE>
    <DATE>2017-11-01 14:20:52</DATE>
    <TEXT>The 99th anniversary is going to be insane</TEXT>
    <INFO>Reddit post</INFO>
  </WRITING>
  <WRITING>
    <TITLE></TITLE>
    <DATE>2017-11-01 14:45:41</DATE>
    <TEXT>WHAT. A. SURPRISE.</TEXT>
    <INFO>Reddit post</INFO>
  </WRITING>
  <WRITING>
    <TITLE></TITLE>
    <DATE>2017-11-01 15:34:26</DATE>
    <TEXT>Oh, what I wouldn't give for an animated series...</TEXT>
    <INFO>Reddit post</INFO>
  </WRITING>
  <WRITING>
    <TITLE></TITLE>
    <DATE>2017-11-04 10:27:45</DATE>
    <TEXT>damn shame</TEXT>
    <INFO>Reddit post</INFO>
  </WRITING>
  <WRITING>
    <TITLE>petition to keep the halloween theme as a permanent dark theme</TITLE>
    <DATE>2017-11-04 10:38:23</DATE>
    <TEXT>title.</TEXT>
    <INFO>Reddit post</INFO>
  </WRITING>
  <WRITING>
    <TITLE></TITLE>
    <DATE>2017-11-04 10:42:15</DATE>
    <TEXT>Our current one feels a little bad on the eyes, especially after looking at it for many hours. The header and red coloring are alright, but the text-background contrast is too high for the sidebar and too low for the main page Mods?</TEXT>
    <INFO>Reddit post</INFO>
  </WRITING>
  <WRITING>
    <TITLE>Just started replaying The Banner Saga. Is the gameplay/combat really as bad as people say it is?</TITLE>
    <DATE>2017-11-14 13:15:16</DATE>
    <TEXT>Personally I welcome the different meta, and i'm not at all bothered by the alternating-turn mechanic. What are your thoughts?</TEXT>
    <INFO>Reddit post</INFO>
  </WRITING>
  <WRITING>
    <TITLE></TITLE>
    <DATE>2017-11-14 14:13:15</DATE>
    <TEXT>In that case, do you prefer the combat in Survival mode or Story mode?</TEXT>
    <INFO>Reddit post</INFO>
  </WRITING>
  <WRITING>
    <TITLE></TITLE>
    <DATE>2017-11-14 14:17:37</DATE>
    <TEXT>The AMA on Wednesday is going to be fucking fantastic</TEXT>
    <INFO>Reddit post</INFO>
  </WRITING>
  <WRITING>
    <TITLE></TITLE>
    <DATE>2017-11-15 02:27:34</DATE>
    <TEXT>Afaik they released a balance patch for that fight</TEXT>
    <INFO>Reddit post</INFO>
  </WRITING>
  <WRITING>
    <TITLE></TITLE>
    <DATE>2017-11-15 13:10:05</DATE>
    <TEXT>This is outrageous, it's unfair.</TEXT>
    <INFO>Reddit post</INFO>
  </WRITING>
  <WRITING>
    <TITLE>If the devs were to release a DLC/in-universe standalone game after all three Sagas are released, what would you want it to be about?</TITLE>
    <DATE>2017-11-15 15:38:15</DATE>
    <TEXT>A small expansion about the Great Wars would be cool</TEXT>
    <INFO>Reddit post</INFO>
  </WRITING>
  <WRITING>
    <TITLE></TITLE>
    <DATE>2017-11-23 04:05:34</DATE>
    <TEXT>I'm sure it's possible, but why go through all that trouble? You can always consult the [wiki](https://bannersaga.gamepedia.com/The_Banner_Saga_Wiki) if you don't recognise a minor character, or you could keep a notepad on hand and write their details down</TEXT>
    <INFO>Reddit post</INFO>
  </WRITING>
  <WRITING>
    <TITLE>*technically a trio*</TITLE>
    <DATE>2017-11-23 10:09:15</DATE>
    <TEXT></TEXT>
    <INFO>Reddit post</INFO>
  </WRITING>
  <WRITING>
    <TITLE></TITLE>
    <DATE>2017-11-23 15:50:39</DATE>
    <TEXT>I'd personally rather take the ARM hit for the extra range. The +STR bonus doesn't really matter since 3rd Rank + Tale is enough to guarantee a KB. More importantly, range is what keeps you outside the reach of enemy archers, so -ARM matters less.</TEXT>
    <INFO>Reddit post</INFO>
  </WRITING>
  <WRITING>
    <TITLE></TITLE>
    <DATE>2017-11-25 13:49:53</DATE>
    <TEXT>is there going to be a linux port of banner saga 2?</TEXT>
    <INFO>Reddit post</INFO>
  </WRITING>
  <WRITING>
    <TITLE></TITLE>
    <DATE>2017-11-25 16:01:19</DATE>
    <TEXT>Who's Karl?</TEXT>
    <INFO>Reddit post</INFO>
  </WRITING>
  <WRITING>
    <TITLE></TITLE>
    <DATE>2017-11-28 17:29:09</DATE>
    <TEXT>Um, I think he's talking about the guy in the middle with his pants down</TEXT>
    <INFO>Reddit post</INFO>
  </WRITING>
  <WRITING>
    <TITLE></TITLE>
    <DATE>2017-11-29 08:20:23</DATE>
    <TEXT>You mean Ubin?</TEXT>
    <INFO>Reddit post</INFO>
  </WRITING>
  <WRITING>
    <TITLE>To the developers: A request to officialize mods</TITLE>
    <DATE>2017-12-03 14:06:24</DATE>
    <TEXT>*Dear Devs,* Would you please consider turning a few community mods into official patches down the line? There is one (or two, depending on how you count it) specific ones which I had in mind: 1. [YaK's SSLTBS1 Fixpack](http://stoicstudio.com/forum/showthread.php?3698-MOD-YaK-s-SSLTBS1-Fixpack-(Spare-Some-Love-To-Banner-Saga-1) 1. [Drake's and YaK's BS2 Fixpack](http://stoicstudio.com/forum/showthread.php?3784-MOD-Drake-s-and-YaK-s-BS2-Fixpack) These are the most popular, but they seem to be outdated all the time. And although you're working on sequel development, they shouldn't be too difficult to implement; it's mostly just some variables to change and assign. *Yours Sincerely,* *subject6309*</TEXT>
    <INFO>Reddit post</INFO>
  </WRITING>
  <WRITING>
    <TITLE></TITLE>
    <DATE>2017-12-03 14:07:20</DATE>
    <TEXT>i've spent way too much time trying to make this rhyme</TEXT>
    <INFO>Reddit post</INFO>
  </WRITING>
  <WRITING>
    <TITLE></TITLE>
    <DATE>2017-12-04 04:54:10</DATE>
    <TEXT>Same story here. Whenever the mods break due to an update I can't bear continuing a playthrough, knowing that there would be missing events and typos abound.</TEXT>
    <INFO>Reddit post</INFO>
  </WRITING>
  <WRITING>
    <TITLE></TITLE>
    <DATE>2017-12-07 16:54:13</DATE>
    <TEXT>I've personally gone with the mobile version, but in the end, it really depends on your needs. Both are the same content-wise; if you prefer the touchscreen interface and like playing games away from home then by all means, go for the mobile experience.</TEXT>
    <INFO>Reddit post</INFO>
  </WRITING>
  <WRITING>
    <TITLE>At what point does it become a warcrime?</TITLE>
    <DATE>2017-12-09 17:47:14</DATE>
    <TEXT></TEXT>
    <INFO>Reddit post</INFO>
  </WRITING>
  <WRITING>
    <TITLE></TITLE>
    <DATE>2017-12-10 09:18:29</DATE>
    <TEXT>The entirety of /u/Nafeij 's post history, up to and including this post</TEXT>
    <INFO>Reddit post</INFO>
  </WRITING>
  <WRITING>
    <TITLE></TITLE>
    <DATE>2017-12-11 15:05:08</DATE>
    <TEXT>Yeah, tell me about it. And whenever I do get around to playing it it usually entails waiting for half an hour in the matchmaking screen.</TEXT>
    <INFO>Reddit post</INFO>
  </WRITING>
  <WRITING>
    <TITLE></TITLE>
    <DATE>2017-12-12 13:39:58</DATE>
    <TEXT>Still waiting for the revival of Turn-based Tactical RPG's... Any day now...</TEXT>
    <INFO>Reddit post</INFO>
  </WRITING>
  <WRITING>
    <TITLE></TITLE>
    <DATE>2017-12-15 02:22:34</DATE>
    <TEXT>I'm all for mod support. I just wish that the devs could try and adopt some of the more pressing bugfix-y ones instead of pushing out minor but otherwise mod-breaking updates.</TEXT>
    <INFO>Reddit post</INFO>
  </WRITING>
  <WRITING>
    <TITLE>Is there a good alternative/fork to Firefox?</TITLE>
    <DATE>2017-12-17 05:42:56</DATE>
    <TEXT></TEXT>
    <INFO>Reddit post</INFO>
  </WRITING>
  <WRITING>
    <TITLE>When is the next Alpha Battle coming out?</TITLE>
    <DATE>2017-12-28 12:40:21</DATE>
    <TEXT>It say's last Friday in the email, but there hasn't been an update yet</TEXT>
    <INFO>Reddit post</INFO>
  </WRITING>
  <WRITING>
    <TITLE></TITLE>
    <DATE>2018-01-02 07:53:52</DATE>
    <TEXT>Oh boy</TEXT>
    <INFO>Reddit post</INFO>
  </WRITING>
  <WRITING>
    <TITLE></TITLE>
    <DATE>2018-01-11 23:31:50</DATE>
    <TEXT>Good move. China has a gigantic market (as PUBG has shown), and fantasy/Strategy games have a big following in East Asia. What *is* concerning is the release on WeGame. If a publisher (see: Tencent) gets exclusive distribution rights down the road, it usually means a loss of dev support and the game ultimately becoming neglected.</TEXT>
    <INFO>Reddit post</INFO>
  </WRITING>
  <WRITING>
    <TITLE></TITLE>
    <DATE>2018-02-02 14:50:40</DATE>
    <TEXT>This bot is amazing</TEXT>
    <INFO>Reddit post</INFO>
  </WRITING>
  <WRITING>
    <TITLE></TITLE>
    <DATE>2018-02-15 03:45:12</DATE>
    <TEXT>You forgot your '/s' there, bud</TEXT>
    <INFO>Reddit post</INFO>
  </WRITING>
  <WRITING>
    <TITLE></TITLE>
    <DATE>2018-02-16 12:14:59</DATE>
    <TEXT>Damn. Right when your journey is coming to an end and things are looking up, the writers go above and beyond to make you feel like a terrible person.</TEXT>
    <INFO>Reddit post</INFO>
  </WRITING>
  <WRITING>
    <TITLE></TITLE>
    <DATE>2018-03-03 03:23:11</DATE>
    <TEXT>Really? I'd always assumed it was an artifact of localization. Do you have any examples?</TEXT>
    <INFO>Reddit post</INFO>
  </WRITING>
  <WRITING>
    <TITLE></TITLE>
    <DATE>2018-03-03 12:44:50</DATE>
    <TEXT>This is seriously awesome. Thanks!</TEXT>
    <INFO>Reddit post</INFO>
  </WRITING>
  <WRITING>
    <TITLE></TITLE>
    <DATE>2018-03-20 23:18:33</DATE>
    <TEXT>I might hold off on a day 1 buy just to see if the port is good. But if it comes in a bundle with the rest of the trilogy I'll buy it before you can say "Dundr's beard".</TEXT>
    <INFO>Reddit post</INFO>
  </WRITING>
  <WRITING>
    <TITLE></TITLE>
    <DATE>2018-04-13 00:20:26</DATE>
    <TEXT>Honestly thought the ports were all going to be released later .this is great news!</TEXT>
    <INFO>Reddit post</INFO>
  </WRITING>
  <WRITING>
    <TITLE></TITLE>
    <DATE>2018-04-14 02:57:53</DATE>
    <TEXT>better yet, give her knockback items and have Aleo continuously buff her with TWT</TEXT>
    <INFO>Reddit post</INFO>
  </WRITING>
  <WRITING>
    <TITLE></TITLE>
    <DATE>2018-04-23 01:28:46</DATE>
    <TEXT>Huh, I never realized it said "ORB #160; #183; WYRM  #183; RAd #160; #183; OMRT(?)" off to the side</TEXT>
    <INFO>Reddit post</INFO>
  </WRITING>
  <WRITING>
    <TITLE></TITLE>
    <DATE>2018-04-24 12:45:56</DATE>
    <TEXT>1. Go to your Steam Library 2. Right click "The Banner Saga 2" if you have it and click Properties. 3. Navigate to General  gt; Set Launch Options. 4. In the popup, type in "Developer" and hit `OK`. 4. Launch the game. You should see a little plus-sign at the top right corner. 5. Press and hold down `Ctrl` `Shift` `~`. This should bring up a console. 6. Enter the following into the console, line by line, and hitting `Enter` after every line. saga bookmark bk_battle_king saga roster_add warped_stoneguard_1 saga roster_add warped_scourge_1 7. Click each of the new icons to add them to the lineup. Good luck and have fun! Edit: Once you're done, repeat steps 1 to 4, but keep the field in 4 blank. If you are experiencing any console errors afterwards, do steps 1 and 2, then navigate to Local Files  gt; Verify Integrity of Game Files</TEXT>
    <INFO>Reddit post</INFO>
  </WRITING>
  <WRITING>
    <TITLE>"You still don't know how to play the game"</TITLE>
    <DATE>2018-04-28 16:18:08</DATE>
    <TEXT></TEXT>
    <INFO>Reddit post</INFO>
  </WRITING>
  <WRITING>
    <TITLE></TITLE>
    <DATE>2018-04-29 13:35:34</DATE>
    <TEXT>He and Meinolf have some sort of history with each other going way back. So I wouldn't be surprised if the King had something to do with that.</TEXT>
    <INFO>Reddit post</INFO>
  </WRITING>
  <WRITING>
    <TITLE></TITLE>
    <DATE>2018-05-07 13:59:47</DATE>
    <TEXT>Too soon</TEXT>
    <INFO>Reddit post</INFO>
  </WRITING>
  <WRITING>
    <TITLE></TITLE>
    <DATE>2018-05-11 00:18:37</DATE>
    <TEXT>i have about 400+ hours on the second game on Steam. it's an ok game.</TEXT>
    <INFO>Reddit post</INFO>
  </WRITING>
  <WRITING>
    <TITLE></TITLE>
    <DATE>2018-05-14 14:13:41</DATE>
    <TEXT>nah, the big downside is that it lacks replayability</TEXT>
    <INFO>Reddit post</INFO>
  </WRITING>
  <WRITING>
    <TITLE></TITLE>
    <DATE>2018-05-19 00:31:43</DATE>
    <TEXT>My favorite one. Absolutely unreal</TEXT>
    <INFO>Reddit post</INFO>
  </WRITING>
  <WRITING>
    <TITLE></TITLE>
    <DATE>2018-05-20 13:59:16</DATE>
    <TEXT>***YOU'VE BEEN HIT BY***</TEXT>
    <INFO>Reddit post</INFO>
  </WRITING>
  <WRITING>
    <TITLE></TITLE>
    <DATE>2018-05-25 08:57:08</DATE>
    <TEXT>it's funny, my dad holds in his sneezes, such that his vocalization of a sneeze is usually louder than the sneeze itself. So he goes "AAAAAAAAARRRR^^^tshk "</TEXT>
    <INFO>Reddit post</INFO>
  </WRITING>
  <WRITING>
    <TITLE></TITLE>
    <DATE>2018-06-17 06:58:36</DATE>
    <TEXT>[Some advice for you](https://youtu.be/jDQDDhLZO-4?t=51s)</TEXT>
    <INFO>Reddit post</INFO>
  </WRITING>
  <WRITING>
    <TITLE>Why did Iver have to go give himself a hand?</TITLE>
    <DATE>2018-06-17 07:30:57</DATE>
    <TEXT>He was two horny</TEXT>
    <INFO>Reddit post</INFO>
  </WRITING>
  <WRITING>
    <TITLE></TITLE>
    <DATE>2018-06-17 07:33:17</DATE>
    <TEXT>You thought this joke was going to be about his lack of arm huh, you sickos.</TEXT>
    <INFO>Reddit post</INFO>
  </WRITING>
  <WRITING>
    <TITLE></TITLE>
    <DATE>2018-06-17 12:02:01</DATE>
    <TEXT>[) ;](https://i.embed.ly/1/image?url=https%3A%2F%2Fthumbs.gfycat.com%2FThinEsteemedAustraliancurlew-size_restricted.gif amp;key=522baf40bd3911e08d854040d3dc5c07)</TEXT>
    <INFO>Reddit post</INFO>
  </WRITING>
  <WRITING>
    <TITLE></TITLE>
    <DATE>2018-06-17 15:20:17</DATE>
    <TEXT>https://youtube.com/watch?v=jDQDDhLZO-4 amp;t=51s amp;feature=youtu.be#</TEXT>
    <INFO>Reddit post</INFO>
  </WRITING>
  <WRITING>
    <TITLE></TITLE>
    <DATE>2018-06-17 15:39:05</DATE>
    <TEXT>https://youtu.be/k-s8jsGtLEs?t=10s</TEXT>
    <INFO>Reddit post</INFO>
  </WRITING>
  <WRITING>
    <TITLE></TITLE>
    <DATE>2018-06-22 14:24:27</DATE>
    <TEXT>[https://renorseful.wordpress.com/tag/the-banner-saga/](https://renorseful.wordpress.com/tag/the-banner-saga/)</TEXT>
    <INFO>Reddit post</INFO>
  </WRITING>
  <WRITING>
    <TITLE>When you're low on Will #127345; #65039;ower</TITLE>
    <DATE>2018-06-24 06:08:05</DATE>
    <TEXT></TEXT>
    <INFO>Reddit post</INFO>
  </WRITING>
  <WRITING>
    <TITLE></TITLE>
    <DATE>2018-06-24 06:22:00</DATE>
    <TEXT>Why I savescum</TEXT>
    <INFO>Reddit post</INFO>
  </WRITING>
  <WRITING>
    <TITLE></TITLE>
    <DATE>2018-06-25 01:11:15</DATE>
    <TEXT>Philistines who play AddictingGames vs Intellectuals whomst disport in Nitrome</TEXT>
    <INFO>Reddit post</INFO>
  </WRITING>
  <WRITING>
    <TITLE></TITLE>
    <DATE>2018-06-25 10:32:53</DATE>
    <TEXT>On the bright side, we'll be getting our very own stonesinger, so hopefully the bullsh*t will cancel out</TEXT>
    <INFO>Reddit post</INFO>
  </WRITING>
  <WRITING>
    <TITLE></TITLE>
    <DATE>2018-06-25 23:46:27</DATE>
    <TEXT>I think I'm about to lose my mind</TEXT>
    <INFO>Reddit post</INFO>
  </WRITING>
  <WRITING>
    <TITLE></TITLE>
    <DATE>2018-06-27 12:57:52</DATE>
    <TEXT>The Banner must fly on...</TEXT>
    <INFO>Reddit post</INFO>
  </WRITING>
  <WRITING>
    <TITLE></TITLE>
    <DATE>2018-06-28 01:59:14</DATE>
    <TEXT>I just glad that they went with Scandinavian voice actors, instead of getting English-speaking VAs to speak with (and botch up) a Scandinavian accent. Could you give some examples of details that caught your attention?</TEXT>
    <INFO>Reddit post</INFO>
  </WRITING>
  <WRITING>
    <TITLE></TITLE>
    <DATE>2018-06-28 02:04:23</DATE>
    <TEXT>It's rather low-magic, which may lend to the realism.</TEXT>
    <INFO>Reddit post</INFO>
  </WRITING>
  <WRITING>
    <TITLE></TITLE>
    <DATE>2018-06-30 02:32:24</DATE>
    <TEXT>Isn't the last 2 minutes or so just tracks from banner saga 2</TEXT>
    <INFO>Reddit post</INFO>
  </WRITING>
  <WRITING>
    <TITLE></TITLE>
    <DATE>2018-06-30 02:34:58</DATE>
    <TEXT>But what is it a reference to?</TEXT>
    <INFO>Reddit post</INFO>
  </WRITING>
  <WRITING>
    <TITLE></TITLE>
    <DATE>2018-07-06 00:19:08</DATE>
    <TEXT>A. Wintory: *So what kind of music do you want next?* Stoic: *Just fuck my shit up* A. Wintory: *Say no more fam*</TEXT>
    <INFO>Reddit post</INFO>
  </WRITING>
  <WRITING>
    <TITLE>i will post one overused meme per day until i beat battle 40 on Survival (Day 1)</TITLE>
    <DATE>2018-07-07 14:22:31</DATE>
    <TEXT></TEXT>
    <INFO>Reddit post</INFO>
  </WRITING>
  <WRITING>
    <TITLE></TITLE>
    <DATE>2018-07-08 09:07:58</DATE>
    <TEXT>You played through the ending of the second game and didn't catch that it was a cliffhanger?</TEXT>
    <INFO>Reddit post</INFO>
  </WRITING>
  <WRITING>
    <TITLE></TITLE>
    <DATE>2018-07-08 14:09:02</DATE>
    <TEXT> gt; Rook/Alette's whole journey was just to get people to safety I'm just gonna let Juno put across the magnitude of Alette/Rook's purpose in saving the world: *"The civilization we have now can live on only if civilized people live. When faced with disaster, we often slip into savagery. You saw what happened in Boersgard."* *....* *Who (the survivors) are when they reach Arberrang is exactly why they are important. Fear will soon spread like flames across dry tinder in that town. Without this caravan's hope, all will be consumed and burned to ash."*</TEXT>
    <INFO>Reddit post</INFO>
  </WRITING>
  <WRITING>
    <TITLE>i will post one overused meme per day until i beat battle 40 on Survival (Day 2)</TITLE>
    <DATE>2018-07-08 14:35:14</DATE>
    <TEXT></TEXT>
    <INFO>Reddit post</INFO>
  </WRITING>
  <WRITING>
    <TITLE></TITLE>
    <DATE>2018-07-08 17:08:44</DATE>
    <TEXT>thanks  lt;3</TEXT>
    <INFO>Reddit post</INFO>
  </WRITING>
  <WRITING>
    <TITLE>i will post one overused meme per day until i beat battle 40 on Survival (Day 3)</TITLE>
    <DATE>2018-07-09 14:32:52</DATE>
    <TEXT></TEXT>
    <INFO>Reddit post</INFO>
  </WRITING>
  <WRITING>
    <TITLE></TITLE>
    <DATE>2018-07-09 14:35:23</DATE>
    <TEXT>[Someone already beat me to it.](https://www.reddit.com/r/bannersaga/comments/8tq7mz/oh_my_gods/?ref=share amp;ref_source=link)</TEXT>
    <INFO>Reddit post</INFO>
  </WRITING>
  <WRITING>
    <TITLE></TITLE>
    <DATE>2018-07-10 13:06:25</DATE>
    <TEXT>b-b-***bLaCk MIRROR***! Get it?!Eksdeeededdd</TEXT>
    <INFO>Reddit post</INFO>
  </WRITING>
  <WRITING>
    <TITLE>i will post one overused meme per day until i beat battle 40 on Survival (Day 4)</TITLE>
    <DATE>2018-07-10 15:45:04</DATE>
    <TEXT></TEXT>
    <INFO>Reddit post</INFO>
  </WRITING>
  <WRITING>
    <TITLE></TITLE>
    <DATE>2018-07-10 15:45:22</DATE>
    <TEXT>help</TEXT>
    <INFO>Reddit post</INFO>
  </WRITING>
  <WRITING>
    <TITLE></TITLE>
    <DATE>2018-07-11 00:56:03</DATE>
    <TEXT>33, Hard</TEXT>
    <INFO>Reddit post</INFO>
  </WRITING>
  <WRITING>
    <TITLE></TITLE>
    <DATE>2018-07-11 03:24:23</DATE>
    <TEXT>I'm 15, and I kind of feel the same way. None of my friends are interested in anything 2D or hand-drawn outside of anime. Don't get me wrong, there are some fantastic examples of Japanese animation out there. Is just that they shun away from stuff like Sleeping Beauty and The Banner Saga because they look 'old-timey'.</TEXT>
    <INFO>Reddit post</INFO>
  </WRITING>
  <WRITING>
    <TITLE>i will post one overused meme per day until i beat battle 40 on Survival (Day 5)</TITLE>
    <DATE>2018-07-11 15:20:25</DATE>
    <TEXT></TEXT>
    <INFO>Reddit post</INFO>
  </WRITING>
  <WRITING>
    <TITLE></TITLE>
    <DATE>2018-07-12 00:16:36</DATE>
    <TEXT>I mostly lurk on the Discord. My stuff gets posted there occasionally, but it's not as well received. tbh I don't enjoy posting these as much now, probably cuz Im running out of ideas. But a promise is a promise.</TEXT>
    <INFO>Reddit post</INFO>
  </WRITING>
  <WRITING>
    <TITLE>i will post one overused meme per day until i beat battle 40 on Survival (Day 6)</TITLE>
    <DATE>2018-07-12 14:57:29</DATE>
    <TEXT></TEXT>
    <INFO>Reddit post</INFO>
  </WRITING>
  <WRITING>
    <TITLE></TITLE>
    <DATE>2018-07-12 23:21:22</DATE>
    <TEXT>thank mr stoic</TEXT>
    <INFO>Reddit post</INFO>
  </WRITING>
  <WRITING>
    <TITLE>Finally</TITLE>
    <DATE>2018-07-13 15:43:18</DATE>
    <TEXT></TEXT>
    <INFO>Reddit post</INFO>
  </WRITING>
  <WRITING>
    <TITLE></TITLE>
    <DATE>2018-07-13 15:46:21</DATE>
    <TEXT>It's been a week, and Battle 40 has been beat. Thanks to everybody for their support on this relatively short journey!</TEXT>
    <INFO>Reddit post</INFO>
  </WRITING>
  <WRITING>
    <TITLE></TITLE>
    <DATE>2018-07-14 01:57:21</DATE>
    <TEXT>Oh, it's not over yet</TEXT>
    <INFO>Reddit post</INFO>
  </WRITING>
  <WRITING>
    <TITLE>MFW replaying the Banner Saga to get Ekkill</TITLE>
    <DATE>2018-07-19 08:11:02</DATE>
    <TEXT></TEXT>
    <INFO>Reddit post</INFO>
  </WRITING>
  <WRITING>
    <TITLE>[TBS3 Spoilers] Soundtrack Tracklist Revealed</TITLE>
    <DATE>2018-07-21 13:47:45</DATE>
    <TEXT></TEXT>
    <INFO>Reddit post</INFO>
  </WRITING>
  <WRITING>
    <TITLE>*Bellows Internally*</TITLE>
    <DATE>2018-07-21 14:48:41</DATE>
    <TEXT></TEXT>
    <INFO>Reddit post</INFO>
  </WRITING>
  <WRITING>
    <TITLE>Conflicts in Sagas</TITLE>
    <DATE>2018-07-22 15:58:25</DATE>
    <TEXT></TEXT>
    <INFO>Reddit post</INFO>
  </WRITING>
  <WRITING>
    <TITLE></TITLE>
    <DATE>2018-07-25 22:12:21</DATE>
    <TEXT>Wasn't this just posted yesterday?</TEXT>
    <INFO>Reddit post</INFO>
  </WRITING>
  <WRITING>
    <TITLE></TITLE>
    <DATE>2018-07-27 19:19:11</DATE>
    <TEXT> gt; You literally get rewarded for letting your caravan starve to death. Fyi, doing this would pretty much make the third game unwinnable.</TEXT>
    <INFO>Reddit post</INFO>
  </WRITING>
  <WRITING>
    <TITLE>[Spoiler-ish] Me filing a class action against Stoic after TBS3:</TITLE>
    <DATE>2018-07-30 12:23:58</DATE>
    <TEXT></TEXT>
    <INFO>Reddit post</INFO>
  </WRITING>
  <WRITING>
    <TITLE></TITLE>
    <DATE>2018-07-30 12:23:59</DATE>
    <TEXT>The ending where [Major Spoilers](#s "everyone dies in Arberrang and turns into Warped, and Iver returns to find nothing but dust.") It got me fucked up man.</TEXT>
    <INFO>Reddit post</INFO>
  </WRITING>
  <WRITING>
    <TITLE>Weapon of Mass Destruction. Upvote so that this is what people see when they Google "Weapon of Mass Destruction".</TITLE>
    <DATE>2018-08-03 03:53:23</DATE>
    <TEXT></TEXT>
    <INFO>Reddit post</INFO>
  </WRITING>
  <WRITING>
    <TITLE></TITLE>
    <DATE>2018-08-14 14:45:06</DATE>
    <TEXT>Yeah... the lack of closure is frustrating, to say the least. After every playthrough I just can't shake the feeling that I've wasted the last 6 years of my life.</TEXT>
    <INFO>Reddit post</INFO>
  </WRITING>
  <WRITING>
    <TITLE></TITLE>
    <DATE>2018-08-16 01:00:55</DATE>
    <TEXT>You should do one for all the main characters :D</TEXT>
    <INFO>Reddit post</INFO>
  </WRITING>
  <WRITING>
    <TITLE></TITLE>
    <DATE>2018-08-17 18:22:17</DATE>
    <TEXT>Look at his post history...</TEXT>
    <INFO>Reddit post</INFO>
  </WRITING>
  <WRITING>
    <TITLE></TITLE>
    <DATE>2018-08-21 12:35:58</DATE>
    <TEXT>It's a good thing Bolverk's a merc and not a woodcutter, or there would be no trees left on the continent.</TEXT>
    <INFO>Reddit post</INFO>
  </WRITING>
  <WRITING>
    <TITLE>It's nice having some visitors for dinner</TITLE>
    <DATE>2018-08-23 14:47:10</DATE>
    <TEXT></TEXT>
    <INFO>Reddit post</INFO>
  </WRITING>
  <WRITING>
    <TITLE></TITLE>
    <DATE>2018-08-23 14:49:21</DATE>
    <TEXT>hi i'm back</TEXT>
    <INFO>Reddit post</INFO>
  </WRITING>
  <WRITING>
    <TITLE>Waiting for a match in Factions got me like</TITLE>
    <DATE>2018-08-24 04:07:38</DATE>
    <TEXT></TEXT>
    <INFO>Reddit post</INFO>
  </WRITING>
  <WRITING>
    <TITLE>The Truth</TITLE>
    <DATE>2018-08-24 12:21:58</DATE>
    <TEXT></TEXT>
    <INFO>Reddit post</INFO>
  </WRITING>
  <WRITING>
    <TITLE>They always ask "Where is Dytch?", but never "How is Dytch?"</TITLE>
    <DATE>2018-08-24 19:03:38</DATE>
    <TEXT></TEXT>
    <INFO>Reddit post</INFO>
  </WRITING>
  <WRITING>
    <TITLE></TITLE>
    <DATE>2018-08-24 19:40:55</DATE>
    <TEXT>It's saddening that we may never get to hear the song about chicken</TEXT>
    <INFO>Reddit post</INFO>
  </WRITING>
  <WRITING>
    <TITLE>Painful mistake</TITLE>
    <DATE>2018-08-24 22:30:18</DATE>
    <TEXT></TEXT>
    <INFO>Reddit post</INFO>
  </WRITING>
  <WRITING>
    <TITLE>Renown and dignity well spent</TITLE>
    <DATE>2018-08-25 01:57:18</DATE>
    <TEXT></TEXT>
    <INFO>Reddit post</INFO>
  </WRITING>
  <WRITING>
    <TITLE>*whispers* For Skogr</TITLE>
    <DATE>2018-08-25 09:03:41</DATE>
    <TEXT></TEXT>
    <INFO>Reddit post</INFO>
  </WRITING>
  <WRITING>
    <TITLE></TITLE>
    <DATE>2018-08-25 09:27:21</DATE>
    <TEXT>I don't recall the exact sequence of events, but if you try to level your heroes past level 5 (in BS 1, with cheats) and modify a bunch of other difficulty-related variables in the save files, the game breaks.</TEXT>
    <INFO>Reddit post</INFO>
  </WRITING>
  <WRITING>
    <TITLE></TITLE>
    <DATE>2018-08-25 13:22:06</DATE>
    <TEXT>fite me Factions 1v1 archers only</TEXT>
    <INFO>Reddit post</INFO>
  </WRITING>
  <WRITING>
    <TITLE>When someone disses your waifu</TITLE>
    <DATE>2018-08-25 14:10:02</DATE>
    <TEXT></TEXT>
    <INFO>Reddit post</INFO>
  </WRITING>
  <WRITING>
    <TITLE></TITLE>
    <DATE>2018-08-25 14:54:48</DATE>
    <TEXT>Bonus: [When you diss them back](http://tinyimg.io/i/2OQOFoe.png)</TEXT>
    <INFO>Reddit post</INFO>
  </WRITING>
  <WRITING>
    <TITLE></TITLE>
    <DATE>2018-08-25 17:03:47</DATE>
    <TEXT> gt; ekkill is a GINGER Thanks for making my point</TEXT>
    <INFO>Reddit post</INFO>
  </WRITING>
  <WRITING>
    <TITLE>The Banner Saga hosts a rich and diverse cast of interesting characters</TITLE>
    <DATE>2018-08-25 19:45:04</DATE>
    <TEXT></TEXT>
    <INFO>Reddit post</INFO>
  </WRITING>
  <WRITING>
    <TITLE></TITLE>
    <DATE>2018-08-26 03:42:49</DATE>
    <TEXT>About as bad as you'd expect. Ever had to fight 4 19STR/22ARM Scourges in BS1?</TEXT>
    <INFO>Reddit post</INFO>
  </WRITING>
  <WRITING>
    <TITLE>We could all at least agree on one thing</TITLE>
    <DATE>2018-08-26 06:04:42</DATE>
    <TEXT></TEXT>
    <INFO>Reddit post</INFO>
  </WRITING>
  <WRITING>
    <TITLE>Running just makes it worse</TITLE>
    <DATE>2018-08-26 18:00:25</DATE>
    <TEXT></TEXT>
    <INFO>Reddit post</INFO>
  </WRITING>
  <WRITING>
    <TITLE>Top Scariest Pictures Taken Seconds From Disaster</TITLE>
    <DATE>2018-08-27 17:00:36</DATE>
    <TEXT></TEXT>
    <INFO>Reddit post</INFO>
  </WRITING>
  <WRITING>
    <TITLE></TITLE>
    <DATE>2018-08-28 07:44:37</DATE>
    <TEXT>It would imply that the devs had planned out the chapters, and by extension the general plot of the whole trilogy, before BS1 was released. Which is insane.</TEXT>
    <INFO>Reddit post</INFO>
  </WRITING>
  <WRITING>
    <TITLE>You merely adopted the shitposts. I was molded by it, raised by it.</TITLE>
    <DATE>2018-08-28 09:13:08</DATE>
    <TEXT></TEXT>
    <INFO>Reddit post</INFO>
  </WRITING>
  <WRITING>
    <TITLE>When you've had two drinks</TITLE>
    <DATE>2018-08-31 05:29:45</DATE>
    <TEXT></TEXT>
    <INFO>Reddit post</INFO>
  </WRITING>
  <WRITING>
    <TITLE></TITLE>
    <DATE>2018-08-31 08:05:09</DATE>
    <TEXT>It's how I hide the pain inside</TEXT>
    <INFO>Reddit post</INFO>
  </WRITING>
  <WRITING>
    <TITLE>Alexa, play 'We are all Guests upon the Land'</TITLE>
    <DATE>2018-08-31 16:37:35</DATE>
    <TEXT></TEXT>
    <INFO>Reddit post</INFO>
  </WRITING>
  <WRITING>
    <TITLE>There's always got to be that one person...</TITLE>
    <DATE>2018-09-01 05:35:30</DATE>
    <TEXT></TEXT>
    <INFO>Reddit post</INFO>
  </WRITING>
  <WRITING>
    <TITLE>The Banner Saga: War Bands</TITLE>
    <DATE>2018-09-01 16:44:28</DATE>
    <TEXT></TEXT>
    <INFO>Reddit post</INFO>
  </WRITING>
  <WRITING>
    <TITLE></TITLE>
    <DATE>2018-09-02 02:27:41</DATE>
    <TEXT>I'm afk at the moment, but the matchmaking is less of an issue for me now. There's usually someone who is online on Discord and available for a match.</TEXT>
    <INFO>Reddit post</INFO>
  </WRITING>
  <WRITING>
    <TITLE>When the fire slinger is not dead and you still don't see where the shatterstone went</TITLE>
    <DATE>2018-09-02 15:32:25</DATE>
    <TEXT></TEXT>
    <INFO>Reddit post</INFO>
  </WRITING>
  <WRITING>
    <TITLE>Press 1F to pay respects</TITLE>
    <DATE>2018-09-03 04:16:02</DATE>
    <TEXT></TEXT>
    <INFO>Reddit post</INFO>
  </WRITING>
  <WRITING>
    <TITLE>N-NANI?</TITLE>
    <DATE>2018-09-03 12:20:04</DATE>
    <TEXT></TEXT>
    <INFO>Reddit post</INFO>
  </WRITING>
  <WRITING>
    <TITLE></TITLE>
    <DATE>2018-09-03 12:36:42</DATE>
    <TEXT>the real dank meme is always in the comments</TEXT>
    <INFO>Reddit post</INFO>
  </WRITING>
  </INDIVIDUAL>